{"translation_id":"drb","book_id":"lamentations","terms":{"aleph":[["1","1"],["2","1"],["3","1"],["3","2"],["3","3"],["4","1"]],"how":[["1","1"],["1","1"],["2","1"],["2","1"],["4","1"],["4","2"]],"doth":[["1","1"]],"the":[["1","1"],["1","1"],["1","1"],["1","1"],["1","2"],["1","3"],["1","3"],["1","3"],["1","4"],["1","4"],["1","5"],["1","5"],["1","5"],["1","5"],["1","6"],["1","6"],["1","6"],["1","7"],["1","7"],["1","7"],["1","7"],["1","9"],["1","10"],["1","10"],["1","11"],["1","12"],["1","12"],["1","12"],["1","13"],["1","14"],["1","14"],["1","15"],["1","15"],["1","15"],["1","15"],["1","15"],["1","15"],["1","16"],["1","16"],["1","16"],["1","17"],["1","18"],["1","19"],["1","20"],["2","1"],["2","1"],["2","1"],["2","1"],["2","1"],["2","2"],["2","2"],["2","2"],["2","2"],["2","2"],["2","2"],["2","3"],["2","3"],["2","4"],["2","4"],["2","5"],["2","5"],["2","5"],["2","5"],["2","6"],["2","6"],["2","7"],["2","7"],["2","7"],["2","7"],["2","7"],["2","7"],["2","7"],["2","7"],["2","8"],["2","8"],["2","8"],["2","8"],["2","8"],["2","9"],["2","9"],["2","9"],["2","9"],["2","10"],["2","10"],["2","10"],["2","10"],["2","10"],["2","11"],["2","11"],["2","11"],["2","11"],["2","11"],["2","11"],["2","11"],["2","12"],["2","12"],["2","12"],["2","12"],["2","13"],["2","15"],["2","15"],["2","15"],["2","15"],["2","15"],["2","16"],["2","16"],["2","17"],["2","17"],["2","17"],["2","17"],["2","18"],["2","18"],["2","18"],["2","18"],["2","19"],["2","19"],["2","19"],["2","19"],["2","19"],["2","19"],["2","19"],["2","19"],["2","20"],["2","20"],["2","20"],["2","20"],["2","21"],["2","21"],["2","21"],["2","21"],["2","21"],["2","22"],["2","22"],["2","22"],["3","1"],["3","1"],["3","3"],["3","13"],["3","14"],["3","18"],["3","19"],["3","19"],["3","22"],["3","22"],["3","24"],["3","25"],["3","25"],["3","26"],["3","27"],["3","29"],["3","31"],["3","32"],["3","33"],["3","34"],["3","34"],["3","35"],["3","35"],["3","35"],["3","36"],["3","37"],["3","38"],["3","38"],["3","40"],["3","41"],["3","41"],["3","45"],["3","45"],["3","48"],["3","48"],["3","50"],["3","50"],["3","51"],["3","53"],["3","55"],["3","57"],["3","58"],["3","58"],["3","62"],["3","62"],["3","64"],["3","66"],["4","1"],["4","1"],["4","1"],["4","1"],["4","1"],["4","2"],["4","2"],["4","2"],["4","2"],["4","3"],["4","3"],["4","3"],["4","3"],["4","3"],["4","4"],["4","4"],["4","4"],["4","4"],["4","5"],["4","5"],["4","6"],["4","6"],["4","6"],["4","7"],["4","7"],["4","8"],["4","9"],["4","9"],["4","9"],["4","10"],["4","10"],["4","10"],["4","10"],["4","11"],["4","11"],["4","12"],["4","12"],["4","12"],["4","12"],["4","12"],["4","12"],["4","12"],["4","13"],["4","13"],["4","13"],["4","13"],["4","13"],["4","14"],["4","15"],["4","16"],["4","16"],["4","16"],["4","16"],["4","16"],["4","18"],["4","19"],["4","19"],["4","19"],["4","19"],["4","20"],["4","20"],["4","20"],["4","21"],["4","21"],["4","22"],["4","22"],["5","5"],["5","6"],["5","9"],["5","9"],["5","9"],["5","10"],["5","10"],["5","11"],["5","11"],["5","11"],["5","12"],["5","12"],["5","12"],["5","13"],["5","13"],["5","13"],["5","14"],["5","14"],["5","14"],["5","14"],["5","14"],["5","15"],["5","16"],["5","21"]],"city":[["1","1"],["1","19"],["2","11"],["2","12"],["2","15"],["3","51"]],"sit":[["1","1"],["2","10"],["3","28"]],"solitary":[["1","1"],["3","28"]],"that":[["1","1"],["1","2"],["1","4"],["1","6"],["1","8"],["1","10"],["1","12"],["1","21"],["1","21"],["2","2"],["2","4"],["2","13"],["2","15"],["2","17"],["2","19"],["2","22"],["2","22"],["2","22"],["3","1"],["3","6"],["3","7"],["3","22"],["3","25"],["3","25"],["3","30"],["3","37"],["3","44"],["3","62"],["4","2"],["4","5"],["4","5"],["4","9"],["4","9"],["4","12"],["4","13"],["4","15"],["4","17"],["4","21"],["5","6"]],"was":[["1","1"],["1","7"],["2","2"],["2","4"],["2","22"],["2","22"],["3","49"],["4","4"],["4","6"],["4","9"],["4","17"],["5","5"],["5","8"],["5","10"]],"full":[["1","1"],["1","20"]],"of":[["1","1"],["1","1"],["1","1"],["1","3"],["1","3"],["1","3"],["1","4"],["1","5"],["1","5"],["1","6"],["1","6"],["1","7"],["1","7"],["1","7"],["1","10"],["1","12"],["1","12"],["1","14"],["1","14"],["1","15"],["1","15"],["1","15"],["1","16"],["1","20"],["1","21"],["1","21"],["1","22"],["1","22"],["2","1"],["2","1"],["2","1"],["2","2"],["2","2"],["2","3"],["2","4"],["2","4"],["2","5"],["2","6"],["2","7"],["2","7"],["2","7"],["2","7"],["2","8"],["2","8"],["2","10"],["2","10"],["2","10"],["2","11"],["2","11"],["2","11"],["2","12"],["2","12"],["2","13"],["2","13"],["2","15"],["2","15"],["2","15"],["2","17"],["2","17"],["2","18"],["2","18"],["2","18"],["2","19"],["2","19"],["2","19"],["2","19"],["2","20"],["2","20"],["2","21"],["2","22"],["2","22"],["3","1"],["3","13"],["3","22"],["3","26"],["3","32"],["3","33"],["3","34"],["3","35"],["3","35"],["3","38"],["3","38"],["3","45"],["3","48"],["3","48"],["3","48"],["3","51"],["3","51"],["3","58"],["3","58"],["3","62"],["3","64"],["3","65"],["4","1"],["4","1"],["4","2"],["4","2"],["4","3"],["4","4"],["4","4"],["4","6"],["4","6"],["4","6"],["4","9"],["4","9"],["4","10"],["4","10"],["4","10"],["4","12"],["4","12"],["4","12"],["4","13"],["4","13"],["4","13"],["4","13"],["4","16"],["4","16"],["4","18"],["4","19"],["4","20"],["4","21"],["4","21"],["4","22"],["4","22"],["4","22"],["5","8"],["5","9"],["5","9"],["5","10"],["5","10"],["5","11"],["5","12"],["5","14"],["5","15"]],"people":[["1","1"],["1","7"],["1","11"],["1","18"],["2","11"],["3","14"],["3","45"],["3","48"],["4","3"],["4","6"],["4","10"]],"is":[["1","1"],["1","2"],["1","4"],["1","6"],["1","8"],["1","9"],["1","9"],["1","9"],["1","14"],["1","16"],["1","17"],["1","17"],["1","18"],["1","20"],["1","20"],["1","21"],["1","22"],["2","5"],["2","9"],["2","11"],["2","12"],["2","13"],["2","15"],["2","16"],["3","10"],["3","17"],["3","18"],["3","23"],["3","24"],["3","25"],["3","26"],["3","27"],["3","37"],["3","47"],["3","49"],["3","53"],["4","1"],["4","1"],["4","3"],["4","6"],["4","8"],["4","8"],["4","8"],["4","18"],["4","20"],["4","22"],["5","1"],["5","2"],["5","15"],["5","15"],["5","16"],["5","17"],["5","18"]],"mistress":[["1","1"]],"gentiles":[["1","1"],["1","10"],["2","9"],["4","15"],["4","20"]],"become":[["1","1"],["1","2"],["1","5"],["1","6"],["1","8"],["1","11"],["2","5"],["3","10"],["3","47"],["4","1"],["4","8"],["5","3"],["5","17"]],"as":[["1","1"],["1","12"],["1","17"],["1","22"],["2","3"],["2","4"],["2","4"],["2","5"],["2","6"],["2","7"],["2","12"],["2","13"],["2","22"],["3","6"],["3","10"],["3","10"],["3","12"],["3","45"],["4","2"],["4","14"],["5","3"],["5","10"],["5","21"]],"a":[["1","1"],["1","9"],["1","12"],["1","13"],["1","14"],["1","17"],["1","21"],["2","3"],["2","6"],["2","7"],["2","7"],["2","18"],["2","20"],["2","22"],["3","10"],["3","10"],["3","12"],["3","14"],["3","27"],["3","35"],["3","36"],["3","37"],["3","39"],["3","44"],["3","47"],["3","47"],["3","52"],["3","53"],["3","64"],["3","65"],["4","6"],["4","11"],["4","17"],["5","3"],["5","20"]],"widow":[["1","1"]],"princes":[["1","1"],["1","6"],["2","2"],["2","9"],["5","12"]],"provinces":[["1","1"]],"made":[["1","1"],["1","12"],["1","13"],["1","22"],["2","2"],["2","7"],["3","4"],["3","7"],["3","11"],["3","14"],["3","45"],["4","6"],["4","8"],["4","21"]],"tributary":[["1","1"]],"beth":[["1","2"],["2","2"],["3","4"],["3","5"],["3","6"],["4","2"]],"weeping":[["1","2"],["2","11"]],"she":[["1","2"],["1","3"],["1","3"],["1","4"],["1","7"],["1","8"],["1","8"],["1","9"],["1","9"],["1","10"]],"hath":[["1","2"],["1","3"],["1","3"],["1","3"],["1","5"],["1","7"],["1","8"],["1","9"],["1","10"],["1","10"],["1","12"],["1","13"],["1","13"],["1","13"],["1","13"],["1","13"],["1","14"],["1","14"],["1","15"],["1","15"],["1","15"],["1","16"],["1","17"],["1","17"],["2","1"],["2","1"],["2","1"],["2","2"],["2","2"],["2","2"],["2","2"],["2","3"],["2","3"],["2","3"],["2","4"],["2","4"],["2","4"],["2","4"],["2","5"],["2","5"],["2","5"],["2","5"],["2","6"],["2","6"],["2","6"],["2","6"],["2","7"],["2","7"],["2","7"],["2","8"],["2","8"],["2","8"],["2","8"],["2","8"],["2","9"],["2","17"],["2","17"],["2","17"],["2","17"],["2","17"],["2","17"],["2","22"],["3","2"],["3","3"],["3","4"],["3","4"],["3","5"],["3","5"],["3","6"],["3","7"],["3","7"],["3","8"],["3","9"],["3","9"],["3","11"],["3","11"],["3","11"],["3","12"],["3","13"],["3","15"],["3","15"],["3","16"],["3","16"],["3","27"],["3","28"],["3","32"],["3","33"],["3","36"],["3","37"],["3","39"],["3","48"],["3","49"],["3","51"],["4","4"],["4","8"],["4","11"],["4","11"],["4","11"],["4","11"],["4","16"],["4","22"]],"wept":[["1","2"]],"in":[["1","2"],["1","3"],["1","4"],["1","7"],["1","12"],["1","14"],["1","19"],["1","20"],["2","1"],["2","1"],["2","2"],["2","2"],["2","3"],["2","3"],["2","4"],["2","5"],["2","6"],["2","7"],["2","7"],["2","11"],["2","12"],["2","12"],["2","17"],["2","19"],["2","19"],["2","20"],["2","21"],["2","22"],["3","6"],["3","10"],["3","10"],["3","11"],["3","21"],["3","25"],["3","29"],["3","36"],["3","41"],["3","43"],["3","45"],["3","57"],["3","66"],["4","1"],["4","3"],["4","5"],["4","5"],["4","6"],["4","6"],["4","8"],["4","10"],["4","11"],["4","12"],["4","13"],["4","14"],["4","14"],["4","17"],["4","18"],["4","19"],["4","19"],["4","20"],["4","21"],["5","9"],["5","11"],["5","11"]],"night":[["1","2"],["2","18"],["2","19"]],"and":[["1","2"],["1","2"],["1","3"],["1","3"],["1","4"],["1","6"],["1","6"],["1","7"],["1","7"],["1","7"],["1","8"],["1","9"],["1","11"],["1","12"],["1","13"],["1","14"],["1","16"],["1","18"],["1","18"],["1","19"],["1","20"],["1","21"],["1","21"],["1","22"],["1","22"],["2","1"],["2","2"],["2","2"],["2","2"],["2","3"],["2","4"],["2","5"],["2","5"],["2","6"],["2","6"],["2","6"],["2","6"],["2","6"],["2","8"],["2","8"],["2","8"],["2","9"],["2","9"],["2","9"],["2","11"],["2","12"],["2","14"],["2","14"],["2","14"],["2","15"],["2","16"],["2","16"],["2","17"],["2","17"],["2","17"],["2","18"],["2","18"],["2","20"],["2","20"],["2","21"],["2","21"],["2","21"],["2","22"],["2","22"],["2","22"],["3","2"],["3","2"],["3","3"],["3","4"],["3","5"],["3","5"],["3","8"],["3","8"],["3","11"],["3","12"],["3","16"],["3","17"],["3","18"],["3","18"],["3","19"],["3","19"],["3","20"],["3","20"],["3","28"],["3","38"],["3","40"],["3","40"],["3","42"],["3","43"],["3","43"],["3","45"],["3","47"],["3","47"],["3","49"],["3","50"],["3","52"],["3","53"],["3","56"],["3","60"],["3","62"],["3","63"],["3","66"],["4","2"],["4","4"],["4","6"],["4","6"],["4","8"],["4","8"],["4","11"],["4","11"],["4","12"],["4","12"],["4","13"],["4","14"],["4","15"],["4","21"],["4","21"],["5","1"],["5","5"],["5","6"],["5","7"],["5","7"],["5","11"],["5","13"],["5","21"]],"her":[["1","2"],["1","2"],["1","2"],["1","2"],["1","2"],["1","2"],["1","2"],["1","3"],["1","3"],["1","3"],["1","3"],["1","3"],["1","4"],["1","4"],["1","4"],["1","5"],["1","5"],["1","5"],["1","5"],["1","5"],["1","5"],["1","6"],["1","6"],["1","7"],["1","7"],["1","7"],["1","7"],["1","7"],["1","8"],["1","8"],["1","8"],["1","9"],["1","9"],["1","9"],["1","10"],["1","10"],["1","11"],["1","17"],["1","17"],["2","9"],["2","9"],["2","9"],["2","9"],["2","9"],["2","16"],["4","6"],["4","7"],["4","13"],["4","13"],["4","13"]],"tears":[["1","2"],["2","18"]],"are":[["1","2"],["1","2"],["1","4"],["1","4"],["1","4"],["1","5"],["1","5"],["1","5"],["1","6"],["1","6"],["1","14"],["1","16"],["1","17"],["1","18"],["1","20"],["1","22"],["2","9"],["2","9"],["2","10"],["2","11"],["2","21"],["3","6"],["3","22"],["3","23"],["4","1"],["4","2"],["4","8"],["4","15"],["4","18"],["5","3"],["5","3"],["5","7"],["5","17"]],"on":[["1","2"],["1","9"],["2","21"],["4","16"]],"cheeks":[["1","2"]],"there":[["1","2"],["1","4"],["1","7"],["1","12"],["1","17"],["1","20"],["1","21"],["2","22"],["3","29"],["3","49"],["4","4"],["5","8"]],"none":[["1","2"],["1","4"],["1","17"],["1","21"],["2","22"],["4","4"],["5","8"]],"to":[["1","2"],["1","2"],["1","4"],["1","10"],["1","11"],["1","12"],["1","14"],["1","15"],["1","17"],["1","18"],["1","19"],["1","21"],["2","1"],["2","2"],["2","4"],["2","6"],["2","6"],["2","6"],["2","8"],["2","10"],["2","12"],["2","13"],["2","13"],["2","13"],["2","14"],["2","14"],["2","17"],["2","18"],["2","19"],["2","22"],["3","10"],["3","14"],["3","25"],["3","25"],["3","26"],["3","30"],["3","32"],["3","34"],["3","35"],["3","36"],["3","37"],["3","40"],["3","41"],["3","42"],["3","47"],["3","64"],["4","3"],["4","4"],["4","4"],["4","8"],["4","15"],["4","17"],["4","20"],["4","21"],["5","2"],["5","2"],["5","6"],["5","6"],["5","8"],["5","16"],["5","19"],["5","21"]],"comfort":[["1","2"],["1","17"],["1","21"],["2","13"]],"among":[["1","2"],["1","3"],["1","17"],["2","9"],["4","15"],["4","15"],["4","20"]],"all":[["1","2"],["1","2"],["1","3"],["1","4"],["1","6"],["1","7"],["1","8"],["1","10"],["1","11"],["1","11"],["1","12"],["1","13"],["1","15"],["1","18"],["1","21"],["1","22"],["1","22"],["2","2"],["2","3"],["2","4"],["2","5"],["2","15"],["2","15"],["2","16"],["2","19"],["3","3"],["3","14"],["3","14"],["3","34"],["3","46"],["3","51"],["3","60"],["3","60"],["3","61"],["3","62"],["4","12"]],"them":[["1","2"],["1","17"],["1","22"],["2","2"],["2","21"],["2","21"],["2","22"],["3","25"],["3","62"],["3","64"],["3","65"],["3","66"],["3","66"],["4","4"],["4","9"],["4","9"],["4","15"],["4","15"],["4","16"],["4","16"]],"were":[["1","2"],["2","3"],["4","2"],["4","5"],["4","5"],["4","7"],["4","9"],["4","10"],["4","14"],["4","17"],["4","19"],["5","5"],["5","5"],["5","12"]],"dear":[["1","2"]],"friends":[["1","2"],["1","19"]],"have":[["1","2"],["1","3"],["1","7"],["1","7"],["1","8"],["1","8"],["1","11"],["1","18"],["1","21"],["1","21"],["1","21"],["2","7"],["2","9"],["2","10"],["2","10"],["2","11"],["2","14"],["2","14"],["2","14"],["2","15"],["2","15"],["2","16"],["2","16"],["2","16"],["2","16"],["2","16"],["2","19"],["3","17"],["3","22"],["3","32"],["3","42"],["3","46"],["3","52"],["3","53"],["3","54"],["3","55"],["4","3"],["4","3"],["4","4"],["4","5"],["4","5"],["4","10"],["4","12"],["4","13"],["4","14"],["4","18"],["5","4"],["5","4"],["5","6"],["5","7"],["5","7"],["5","8"],["5","14"],["5","16"],["5","18"]],"despised":[["1","2"],["1","8"]],"enemies":[["1","2"],["1","5"],["1","7"],["1","17"],["1","21"],["2","16"],["3","46"],["3","52"]],"ghimel":[["1","3"],["2","3"],["3","7"],["3","8"],["3","9"],["4","3"]],"juda":[["1","3"],["1","15"],["2","2"],["2","5"],["5","11"]],"removed":[["1","3"],["3","17"],["4","15"]],"dwelling":[["1","3"]],"place":[["1","3"]],"because":[["1","3"],["1","4"],["1","5"],["1","8"],["1","9"],["1","16"],["1","16"],["3","22"],["3","28"],["3","49"],["3","51"],["5","9"],["5","16"],["5","18"]],"affliction":[["1","3"],["1","4"],["1","7"],["1","9"]],"greatness":[["1","3"]],"bondage":[["1","3"]],"dwelt":[["1","3"]],"nations":[["1","3"]],"found":[["1","3"],["2","9"],["2","16"]],"no":[["1","3"],["1","6"],["1","7"],["2","9"],["2","9"],["2","18"],["2","21"],["3","49"],["4","15"],["4","16"],["4","22"],["5","5"]],"rest":[["1","3"],["2","18"],["3","49"],["5","5"]],"persecutors":[["1","3"],["4","19"]],"taken":[["1","3"],["1","15"],["3","28"],["4","20"]],"midst":[["1","3"],["1","15"],["3","45"],["4","13"]],"straits":[["1","3"]],"daleth":[["1","4"],["2","4"],["3","10"],["3","11"],["3","12"],["4","4"]],"ways":[["1","4"],["3","9"],["3","40"]],"sion":[["1","4"],["1","6"],["1","17"],["2","1"],["2","4"],["2","6"],["2","8"],["2","10"],["2","13"],["2","18"],["4","2"],["4","11"],["4","22"],["5","11"],["5","18"]],"mourn":[["1","4"]],"come":[["1","4"],["4","18"],["4","21"],["5","1"]],"solemn":[["1","4"],["2","7"]],"feast":[["1","4"],["2","7"]],"gates":[["1","4"],["2","9"],["4","12"],["5","14"]],"broken":[["1","4"],["2","3"],["2","9"],["3","4"],["3","11"],["3","16"]],"down":[["1","4"],["1","9"],["1","16"],["2","1"],["2","2"],["2","2"],["2","5"],["2","6"],["2","10"],["2","18"],["3","9"],["3","48"],["3","50"],["3","63"]],"priests":[["1","4"],["1","19"],["4","13"],["4","16"]],"sigh":[["1","4"],["1","11"],["1","21"]],"virgins":[["1","4"],["1","18"],["2","10"],["2","21"],["5","11"]],"oppressed":[["1","4"],["5","11"]],"with":[["1","4"],["1","13"],["1","16"],["2","1"],["2","10"],["2","10"],["2","11"],["2","16"],["2","20"],["3","5"],["3","9"],["3","15"],["3","15"],["3","16"],["3","26"],["3","30"],["3","41"],["3","48"],["4","2"],["4","9"],["4","9"],["4","9"],["4","14"],["5","6"]],"bitterness":[["1","4"],["1","20"],["3","15"]],"he":[["1","5"],["1","12"],["1","13"],["1","13"],["1","13"],["1","13"],["1","15"],["2","1"],["2","2"],["2","2"],["2","3"],["2","3"],["2","3"],["2","4"],["2","4"],["2","4"],["2","4"],["2","5"],["2","5"],["2","5"],["2","5"],["2","6"],["2","6"],["2","7"],["2","7"],["2","8"],["2","9"],["2","17"],["2","17"],["2","17"],["2","17"],["2","17"],["3","2"],["3","3"],["3","4"],["3","4"],["3","5"],["3","5"],["3","6"],["3","7"],["3","7"],["3","8"],["3","9"],["3","9"],["3","10"],["3","11"],["3","11"],["3","12"],["3","13"],["3","13"],["3","14"],["3","15"],["3","15"],["3","15"],["3","16"],["3","16"],["3","27"],["3","28"],["3","28"],["3","29"],["3","30"],["3","30"],["3","32"],["3","32"],["3","33"],["3","37"],["4","5"],["4","11"],["4","11"],["4","15"],["4","16"],["4","22"],["4","22"],["4","22"]],"adversaries":[["1","5"],["2","17"]],"lords":[["1","5"]],"enriched":[["1","5"]],"lord":[["1","5"],["1","9"],["1","11"],["1","12"],["1","14"],["1","15"],["1","15"],["1","17"],["1","18"],["1","20"],["2","1"],["2","2"],["2","5"],["2","6"],["2","7"],["2","7"],["2","8"],["2","9"],["2","17"],["2","18"],["2","19"],["2","20"],["2","20"],["2","22"],["3","18"],["3","22"],["3","24"],["3","25"],["3","31"],["3","36"],["3","37"],["3","40"],["3","41"],["3","50"],["3","55"],["3","58"],["3","59"],["3","61"],["3","64"],["3","66"],["4","11"],["4","16"],["4","20"],["5","1"],["5","19"],["5","21"]],"spoken":[["1","5"]],"against":[["1","5"],["1","15"],["1","17"],["2","16"],["3","3"],["3","7"],["3","46"],["3","59"],["3","60"],["3","61"],["3","62"],["3","62"],["5","22"]],"for":[["1","5"],["1","10"],["1","11"],["1","11"],["1","12"],["1","13"],["1","15"],["1","18"],["1","19"],["1","20"],["1","20"],["1","22"],["1","22"],["2","11"],["2","13"],["2","14"],["2","14"],["2","16"],["2","19"],["2","19"],["3","6"],["3","12"],["3","24"],["3","26"],["3","27"],["3","31"],["3","31"],["3","32"],["3","33"],["3","39"],["3","48"],["4","4"],["4","4"],["4","9"],["4","9"],["4","13"],["4","15"],["4","17"],["4","18"],["4","19"],["5","4"],["5","18"],["5","19"],["5","20"],["5","20"]],"multitude":[["1","5"],["3","32"]],"iniquities":[["1","5"],["1","14"],["1","22"],["4","13"],["5","7"]],"children":[["1","5"],["1","16"],["2","11"],["2","19"],["2","20"],["3","33"],["4","10"],["5","13"]],"led":[["1","5"],["3","2"]],"into":[["1","5"],["1","10"],["1","10"],["1","13"],["1","14"],["1","18"],["2","7"],["2","9"],["3","2"],["3","2"],["3","13"],["3","53"],["4","22"],["5","15"]],"captivity":[["1","5"],["1","18"],["4","22"]],"before":[["1","5"],["1","6"],["1","22"],["2","3"],["2","19"],["3","35"],["3","44"]],"face":[["1","5"],["1","6"],["2","19"],["3","35"],["4","8"],["4","16"]],"oppressor":[["1","5"]],"vau":[["1","6"],["2","6"],["3","16"],["3","17"],["3","18"],["4","6"]],"from":[["1","6"],["1","7"],["1","13"],["1","16"],["2","1"],["2","3"],["2","8"],["2","9"],["3","17"],["3","18"],["3","27"],["3","50"],["3","55"],["3","56"],["3","66"],["5","14"],["5","14"],["5","16"],["5","19"],["5","21"]],"daughter":[["1","6"],["1","15"],["2","1"],["2","4"],["2","5"],["2","8"],["2","10"],["2","11"],["2","13"],["2","13"],["2","15"],["2","18"],["3","48"],["4","3"],["4","6"],["4","10"],["4","21"],["4","22"],["4","22"]],"beauty":[["1","6"],["2","15"]],"departed":[["1","6"]],"like":[["1","6"],["1","12"],["1","21"],["2","4"],["2","18"],["2","19"],["3","52"],["4","3"],["4","8"]],"rams":[["1","6"]],"find":[["1","6"]],"pastures":[["1","6"]],"they":[["1","6"],["1","8"],["1","10"],["1","11"],["1","11"],["1","14"],["1","19"],["1","19"],["1","21"],["1","21"],["1","21"],["2","7"],["2","10"],["2","10"],["2","10"],["2","12"],["2","12"],["2","12"],["2","14"],["2","14"],["2","15"],["2","15"],["2","16"],["3","23"],["3","53"],["4","2"],["4","2"],["4","3"],["4","5"],["4","5"],["4","8"],["4","10"],["4","14"],["4","14"],["4","14"],["4","14"],["4","15"],["4","15"],["4","15"],["4","16"],["4","16"],["4","19"],["4","19"],["5","11"],["5","12"],["5","13"]],"gone":[["1","6"],["1","18"]],"away":[["1","6"],["1","15"],["1","19"],["2","11"],["2","12"],["3","56"],["4","9"],["4","22"]],"without":[["1","6"],["2","21"],["3","52"],["5","3"]],"strength":[["1","6"],["1","14"]],"pursuer":[["1","6"]],"zain":[["1","7"],["2","7"],["3","19"],["3","20"],["3","21"],["4","7"]],"jerusalem":[["1","7"],["1","8"],["1","17"],["2","10"],["2","13"],["2","15"],["4","12"]],"remembered":[["1","7"],["1","9"],["2","1"]],"days":[["1","7"],["1","7"],["2","17"],["4","18"],["5","21"]],"prevarication":[["1","7"]],"desirable":[["1","7"],["1","10"]],"things":[["1","7"],["1","10"],["1","11"],["2","14"],["3","17"],["3","21"]],"which":[["1","7"],["1","14"],["2","16"],["2","17"],["2","17"],["4","6"]],"had":[["1","7"],["4","16"]],"old":[["1","7"],["2","17"],["2","21"],["3","4"],["4","7"]],"when":[["1","7"],["2","11"],["2","12"],["2","12"],["3","8"],["3","27"],["3","37"],["3","57"],["4","14"],["4","17"]],"fell":[["1","7"],["5","13"]],"enemy":[["1","7"],["1","9"],["1","10"],["1","16"],["2","3"],["2","4"],["2","5"],["2","7"],["2","17"],["2","22"],["4","12"]],"s":[["1","7"],["4","2"]],"hand":[["1","7"],["1","10"],["1","14"],["1","14"],["2","3"],["2","4"],["2","7"],["2","8"],["3","3"],["5","6"],["5","8"],["5","12"]],"helper":[["1","7"]],"seen":[["1","7"],["1","8"],["1","10"],["2","14"],["2","14"],["2","16"],["3","59"],["3","60"]],"mocked":[["1","7"]],"at":[["1","7"],["1","20"],["2","15"],["2","15"],["2","19"],["5","9"]],"sabbaths":[["1","7"],["2","6"]],"heth":[["1","8"],["2","8"],["3","22"],["3","23"],["3","24"],["4","8"]],"grievously":[["1","8"]],"sinned":[["1","8"],["5","7"],["5","16"]],"therefore":[["1","8"],["1","16"],["3","21"],["3","24"],["3","42"],["5","17"],["5","17"]],"unstable":[["1","8"]],"honoured":[["1","8"]],"shame":[["1","8"]],"but":[["1","8"],["1","19"],["2","14"],["5","19"],["5","22"]],"sighed":[["1","8"]],"turned":[["1","8"],["1","13"],["1","20"],["3","3"],["3","3"],["3","9"],["3","11"],["5","2"],["5","15"]],"backward":[["1","8"]],"teth":[["1","9"],["2","9"],["3","25"],["3","26"],["3","27"],["4","9"]],"filthiness":[["1","9"]],"feet":[["1","9"],["1","13"],["3","34"]],"not":[["1","9"],["1","9"],["1","10"],["1","14"],["2","1"],["2","2"],["2","8"],["2","14"],["2","17"],["2","18"],["3","2"],["3","7"],["3","22"],["3","22"],["3","31"],["3","33"],["3","36"],["3","37"],["3","38"],["3","43"],["3","44"],["3","49"],["3","56"],["3","57"],["4","8"],["4","12"],["4","14"],["4","15"],["4","16"],["4","17"],["5","7"],["5","12"]],"end":[["1","9"],["3","18"],["4","18"],["4","18"]],"wonderfully":[["1","9"]],"cast":[["1","9"],["2","1"],["2","2"],["2","5"],["2","7"],["3","31"],["3","32"],["3","33"]],"having":[["1","9"]],"comforter":[["1","9"],["1","16"]],"behold":[["1","9"],["1","20"],["2","4"],["2","20"],["3","63"],["5","1"]],"o":[["1","9"],["1","11"],["1","12"],["1","20"],["2","13"],["2","13"],["2","20"],["3","55"],["3","58"],["3","59"],["3","61"],["3","64"],["3","66"],["4","21"],["4","22"],["4","22"],["5","1"],["5","19"],["5","21"]],"my":[["1","9"],["1","12"],["1","13"],["1","13"],["1","14"],["1","14"],["1","14"],["1","15"],["1","15"],["1","16"],["1","16"],["1","16"],["1","18"],["1","18"],["1","18"],["1","19"],["1","19"],["1","19"],["1","20"],["1","20"],["1","21"],["1","21"],["1","22"],["1","22"],["1","22"],["2","11"],["2","11"],["2","11"],["2","11"],["2","21"],["2","21"],["2","22"],["3","1"],["3","4"],["3","4"],["3","4"],["3","7"],["3","8"],["3","9"],["3","9"],["3","11"],["3","13"],["3","14"],["3","16"],["3","17"],["3","18"],["3","18"],["3","19"],["3","20"],["3","21"],["3","24"],["3","24"],["3","48"],["3","48"],["3","49"],["3","51"],["3","51"],["3","51"],["3","52"],["3","53"],["3","54"],["3","56"],["3","56"],["3","58"],["3","58"],["3","59"],["4","3"],["4","6"],["4","10"]],"lifted":[["1","9"]],"up":[["1","9"],["2","6"],["2","16"],["2","17"],["2","19"],["2","22"],["3","9"],["3","28"],["3","41"],["3","62"],["3","63"],["4","5"],["4","14"],["5","12"]],"jod":[["1","10"],["2","10"],["3","28"],["3","29"],["3","30"],["4","10"]],"put":[["1","10"],["1","14"],["3","29"]],"out":[["1","10"],["1","14"],["1","15"],["2","4"],["2","8"],["2","11"],["2","12"],["2","19"],["3","7"],["3","8"],["3","38"],["4","3"],["4","11"],["4","15"],["5","8"]],"his":[["1","10"],["1","12"],["1","14"],["1","17"],["1","18"],["2","1"],["2","1"],["2","1"],["2","2"],["2","3"],["2","3"],["2","4"],["2","4"],["2","4"],["2","5"],["2","6"],["2","6"],["2","6"],["2","7"],["2","7"],["2","8"],["2","8"],["2","17"],["3","1"],["3","3"],["3","12"],["3","12"],["3","13"],["3","22"],["3","27"],["3","28"],["3","29"],["3","30"],["3","32"],["3","34"],["3","36"],["3","39"],["4","4"],["4","11"],["4","11"]],"enter":[["1","10"],["1","10"],["4","12"]],"sanctuary":[["1","10"],["2","7"],["2","20"],["4","1"]],"whom":[["1","10"],["2","20"],["4","20"]],"thou":[["1","10"],["1","21"],["1","21"],["1","22"],["2","20"],["2","21"],["2","21"],["2","22"],["3","42"],["3","43"],["3","43"],["3","44"],["3","45"],["3","56"],["3","57"],["3","57"],["3","58"],["3","58"],["3","59"],["3","59"],["3","60"],["3","61"],["3","64"],["3","65"],["3","66"],["4","21"],["5","19"],["5","20"],["5","20"],["5","22"],["5","22"]],"gavest":[["1","10"]],"commandment":[["1","10"]],"should":[["1","10"],["2","22"],["4","12"]],"thy":[["1","10"],["2","13"],["2","14"],["2","14"],["2","16"],["2","17"],["2","18"],["2","19"],["2","19"],["2","19"],["2","21"],["3","23"],["3","43"],["3","55"],["3","56"],["3","65"],["4","20"],["4","22"],["4","22"],["4","22"],["5","19"]],"church":[["1","10"]],"caph":[["1","11"],["2","11"],["3","31"],["3","32"],["3","33"],["4","11"]],"seek":[["1","11"],["3","40"]],"bread":[["1","11"],["4","4"],["5","6"],["5","9"]],"given":[["1","11"],["4","3"],["5","5"],["5","6"]],"their":[["1","11"],["1","19"],["1","19"],["1","22"],["2","10"],["2","10"],["2","10"],["2","12"],["2","12"],["2","12"],["2","15"],["2","15"],["2","16"],["2","18"],["2","20"],["2","20"],["3","14"],["3","46"],["3","59"],["3","60"],["3","60"],["3","61"],["3","61"],["3","62"],["3","63"],["3","63"],["3","63"],["3","64"],["4","3"],["4","8"],["4","8"],["4","8"],["4","10"],["4","10"],["4","14"],["5","7"],["5","8"],["5","12"]],"precious":[["1","11"]],"food":[["1","11"],["1","19"]],"relieve":[["1","11"],["1","19"]],"soul":[["1","11"],["1","16"],["3","17"],["3","20"],["3","24"],["3","25"],["3","51"],["3","58"]],"see":[["1","11"],["1","12"],["1","18"],["3","1"]],"consider":[["1","11"],["2","20"],["5","1"]],"i":[["1","11"],["1","14"],["1","16"],["1","18"],["1","18"],["1","19"],["1","20"],["1","20"],["1","21"],["2","13"],["2","13"],["2","13"],["2","13"],["2","22"],["3","1"],["3","7"],["3","8"],["3","14"],["3","17"],["3","18"],["3","20"],["3","21"],["3","21"],["3","24"],["3","54"],["3","54"],["3","55"],["3","57"],["3","63"]],"am":[["1","11"],["1","14"],["1","20"],["1","20"],["3","1"],["3","14"],["3","54"],["3","63"]],"vile":[["1","11"]],"lamed":[["1","12"],["2","12"],["3","34"],["3","35"],["3","36"],["4","12"]],"ye":[["1","12"],["1","18"],["4","15"]],"pass":[["1","12"],["3","44"]],"by":[["1","12"],["2","15"],["2","21"],["3","1"],["3","16"],["4","9"],["4","12"],["5","5"],["5","10"],["5","12"]],"way":[["1","12"],["2","15"],["4","18"]],"attend":[["1","12"]],"if":[["1","12"],["3","29"],["3","32"]],"be":[["1","12"],["1","21"],["1","22"],["2","6"],["2","20"],["3","20"],["3","29"],["3","29"],["3","30"],["3","37"],["4","21"],["4","21"],["5","6"],["5","21"]],"any":[["1","12"]],"sorrow":[["1","12"],["1","12"],["1","13"],["1","18"]],"vintage":[["1","12"],["1","22"],["1","22"]],"me":[["1","12"],["1","13"],["1","13"],["1","13"],["1","14"],["1","15"],["1","15"],["1","16"],["1","19"],["1","20"],["1","21"],["1","21"],["1","22"],["2","22"],["3","2"],["3","2"],["3","3"],["3","5"],["3","5"],["3","6"],["3","7"],["3","10"],["3","11"],["3","11"],["3","12"],["3","15"],["3","15"],["3","16"],["3","20"],["3","45"],["3","52"],["3","52"],["3","53"],["3","59"],["3","60"],["3","61"],["3","62"],["3","62"]],"spoke":[["1","12"]],"day":[["1","12"],["1","13"],["1","21"],["2","1"],["2","7"],["2","16"],["2","18"],["2","21"],["2","22"],["3","3"],["3","14"],["3","57"],["3","62"]],"fierce":[["1","12"],["2","3"],["4","11"]],"anger":[["1","12"],["2","1"],["2","3"],["3","66"],["4","11"]],"mem":[["1","13"],["2","13"],["3","37"],["3","38"],["3","39"],["4","13"]],"above":[["1","13"]],"sent":[["1","13"]],"fire":[["1","13"],["2","3"],["2","4"],["4","11"]],"bones":[["1","13"],["3","4"],["4","8"]],"chastised":[["1","13"]],"spread":[["1","13"],["1","17"]],"net":[["1","13"]],"back":[["1","13"],["2","3"]],"desolate":[["1","13"],["1","16"],["3","11"]],"wasted":[["1","13"],["3","51"]],"long":[["1","13"],["2","20"],["3","14"],["5","20"]],"nun":[["1","14"],["2","14"],["3","40"],["3","41"],["3","42"],["4","14"]],"yoke":[["1","14"],["3","27"]],"watched":[["1","14"]],"folded":[["1","14"]],"together":[["1","14"],["2","8"]],"upon":[["1","14"],["2","10"],["2","11"],["2","18"],["3","28"],["3","55"],["3","57"],["4","19"],["5","1"],["5","18"]],"neck":[["1","14"]],"weakened":[["1","14"]],"delivered":[["1","14"],["2","6"],["2","7"]],"able":[["1","14"],["4","17"]],"rise":[["1","14"],["3","62"]],"samech":[["1","15"],["2","15"],["3","43"],["3","44"],["3","45"],["4","15"]],"mighty":[["1","15"]],"men":[["1","15"],["1","15"],["1","18"],["2","5"],["2","21"],["3","33"],["4","14"],["5","13"],["5","14"]],"called":[["1","15"],["1","19"],["2","22"],["3","55"],["3","57"]],"time":[["1","15"],["5","20"]],"destroy":[["1","15"],["2","8"],["3","36"],["3","66"]],"chosen":[["1","15"]],"trodden":[["1","15"]],"winepress":[["1","15"]],"virgin":[["1","15"],["2","2"],["2","13"]],"ain":[["1","16"],["2","17"],["3","49"],["3","50"],["3","51"],["4","17"]],"do":[["1","16"]],"weep":[["1","16"]],"eyes":[["1","16"],["2","11"],["4","17"],["5","17"]],"run":[["1","16"],["2","18"],["3","48"]],"water":[["1","16"],["2","19"],["3","48"],["5","4"]],"relief":[["1","16"]],"far":[["1","16"],["3","17"]],"prevailed":[["1","16"]],"phe":[["1","17"],["2","16"],["3","46"],["3","47"],["3","48"],["4","16"]],"forth":[["1","17"]],"hands":[["1","17"],["2","15"],["2","19"],["3","41"],["3","64"],["4","2"],["4","6"],["4","10"]],"commanded":[["1","17"],["2","17"],["3","37"]],"jacob":[["1","17"],["2","2"],["2","3"]],"round":[["1","17"],["2","3"],["2","22"],["3","5"],["3","7"]],"about":[["1","17"],["2","3"],["2","22"],["3","5"],["3","7"]],"him":[["1","17"],["2","19"],["3","24"],["3","25"],["3","25"],["3","30"],["3","30"]],"menstruous":[["1","17"]],"woman":[["1","17"]],"sade":[["1","18"],["2","18"],["3","52"],["3","53"],["3","54"],["4","18"]],"just":[["1","18"],["4","13"]],"provoked":[["1","18"],["3","42"]],"mouth":[["1","18"],["2","16"],["3","29"],["3","38"],["4","4"],["4","20"]],"wrath":[["1","18"],["2","1"],["2","2"],["2","6"],["2","21"],["2","22"],["3","42"],["3","43"],["4","11"]],"hear":[["1","18"]],"pray":[["1","18"]],"you":[["1","18"],["4","15"]],"young":[["1","18"],["2","21"],["4","3"],["5","13"],["5","14"]],"coph":[["1","19"],["2","19"],["3","55"],["3","56"],["3","57"],["4","19"]],"deceived":[["1","19"]],"ancients":[["1","19"],["2","10"],["5","14"]],"pined":[["1","19"],["4","9"]],"while":[["1","19"],["4","17"]],"sought":[["1","19"]],"souls":[["1","19"],["2","12"]],"res":[["1","20"],["2","20"],["3","58"],["3","59"],["3","60"],["4","20"]],"distress":[["1","20"]],"bowels":[["1","20"],["2","11"]],"troubled":[["1","20"],["2","11"]],"heart":[["1","20"],["1","22"],["2","18"],["2","19"],["3","21"],["3","65"],["5","15"],["5","17"]],"within":[["1","20"],["3","20"]],"abroad":[["1","20"]],"sword":[["1","20"],["2","21"],["4","9"],["5","9"]],"destroyeth":[["1","20"]],"home":[["1","20"]],"death":[["1","20"]],"alike":[["1","20"]],"sin":[["1","21"],["2","21"],["3","61"],["3","62"],["3","63"],["4","6"],["4","21"]],"heard":[["1","21"],["1","21"],["3","56"],["3","61"]],"evil":[["1","21"],["1","22"],["3","38"]],"rejoiced":[["1","21"]],"hast":[["1","21"],["1","21"],["1","22"],["2","20"],["2","21"],["2","21"],["2","22"],["3","43"],["3","43"],["3","43"],["3","43"],["3","44"],["3","45"],["3","56"],["3","58"],["3","59"],["3","60"],["3","61"],["5","22"]],"done":[["1","21"],["2","17"],["3","37"],["3","42"]],"it":[["1","21"],["2","3"],["2","16"],["2","16"],["3","26"],["3","27"],["3","28"],["3","37"],["4","4"],["4","8"],["4","9"],["4","11"],["4","14"],["5","18"],["5","18"]],"brought":[["1","21"],["2","2"],["2","22"],["3","2"],["4","5"]],"consolation":[["1","21"]],"shall":[["1","21"],["2","13"],["2","13"],["2","13"],["2","13"],["2","20"],["2","20"],["3","20"],["3","21"],["3","28"],["3","29"],["3","30"],["3","30"],["3","38"],["4","20"],["4","21"],["5","21"]],"unto":[["1","21"],["4","4"]],"thau":[["1","22"],["2","22"],["3","64"],["3","65"],["3","66"],["4","22"]],"let":[["1","22"],["2","18"],["2","18"],["3","40"],["3","41"]],"present":[["1","22"]],"thee":[["1","22"],["2","13"],["2","13"],["2","13"],["2","13"],["2","13"],["2","14"],["2","14"],["2","14"],["2","15"],["2","16"],["2","17"],["3","42"],["3","44"],["3","57"],["4","21"],["4","22"],["5","21"]],"make":[["1","22"]],"sighs":[["1","22"],["3","56"]],"many":[["1","22"]],"sorrowful":[["1","22"],["5","17"]],"covered":[["2","1"],["3","43"]],"obscurity":[["2","1"]],"heaven":[["2","1"]],"earth":[["2","1"],["2","11"],["2","15"],["4","9"],["4","12"]],"glorious":[["2","1"]],"one":[["2","1"],["3","16"],["3","16"]],"israel":[["2","1"],["2","3"],["2","5"]],"footstool":[["2","1"]],"headlong":[["2","2"],["2","5"]],"spared":[["2","2"],["2","17"],["3","43"]],"beautiful":[["2","2"]],"destroyed":[["2","2"],["2","5"],["2","6"],["2","8"],["2","9"],["2","17"],["5","18"]],"strong":[["2","2"],["2","5"]],"holds":[["2","2"],["2","5"]],"ground":[["2","2"],["2","9"],["2","10"],["2","10"],["2","21"]],"kingdom":[["2","2"]],"unclean":[["2","2"]],"thereof":[["2","2"],["2","5"],["2","7"],["4","11"]],"horn":[["2","3"],["2","17"]],"drawn":[["2","3"],["4","3"]],"right":[["2","3"],["2","4"]],"kindled":[["2","3"],["4","11"]],"flaming":[["2","3"]],"devouring":[["2","3"]],"bent":[["2","4"],["3","12"]],"bow":[["2","4"],["3","12"]],"an":[["2","4"],["2","4"],["2","5"],["3","45"],["5","10"]],"fixed":[["2","4"]],"adversary":[["2","4"],["4","12"]],"killed":[["2","4"],["2","21"],["3","43"]],"fair":[["2","4"]],"tabernacle":[["2","4"],["2","6"]],"poured":[["2","4"],["2","11"],["4","11"]],"indignation":[["2","4"],["2","6"],["3","1"]],"overthrown":[["2","5"],["4","6"]],"walls":[["2","5"],["2","7"],["2","18"]],"multiplied":[["2","5"]],"afflicted":[["2","5"],["3","33"],["3","49"]],"both":[["2","5"],["3","38"]],"women":[["2","5"],["2","20"],["4","10"],["5","11"]],"tent":[["2","6"]],"garden":[["2","6"]],"thrown":[["2","6"]],"caused":[["2","6"],["2","17"]],"feasts":[["2","6"]],"forgotten":[["2","6"],["3","17"]],"king":[["2","6"],["2","9"]],"priest":[["2","6"],["2","20"]],"reproach":[["2","6"],["3","61"],["5","1"]],"off":[["2","7"],["3","17"],["3","31"],["3","32"],["3","33"],["3","54"]],"altar":[["2","7"]],"cursed":[["2","7"]],"towers":[["2","7"]],"noise":[["2","7"]],"house":[["2","7"]],"purposed":[["2","8"],["2","17"]],"wall":[["2","8"],["2","8"]],"stretched":[["2","8"]],"line":[["2","8"]],"withdrawn":[["2","8"]],"destroying":[["2","8"]],"bulwark":[["2","8"]],"mourned":[["2","8"]],"been":[["2","8"],["3","49"]],"sunk":[["2","9"]],"bars":[["2","9"]],"law":[["2","9"]],"more":[["2","9"],["4","7"],["4","15"],["4","16"],["4","22"]],"prophets":[["2","9"],["2","14"],["4","13"]],"vision":[["2","9"]],"held":[["2","10"],["4","14"]],"peace":[["2","10"],["3","17"],["3","28"]],"sprinkled":[["2","10"]],"heads":[["2","10"],["2","10"],["2","15"]],"dust":[["2","10"],["3","29"]],"girded":[["2","10"]],"haircloth":[["2","10"]],"hang":[["2","10"]],"failed":[["2","11"],["3","22"],["4","17"]],"liver":[["2","11"]],"destruction":[["2","11"],["2","13"],["3","47"],["3","48"],["4","10"]],"sucklings":[["2","11"]],"fainted":[["2","11"],["2","12"],["2","19"]],"streets":[["2","11"],["2","12"],["2","19"],["4","5"],["4","8"],["4","14"],["4","18"]],"said":[["2","12"],["2","16"],["3","18"],["3","24"],["3","54"],["4","15"],["4","20"]],"mothers":[["2","12"],["2","12"],["5","3"]],"where":[["2","12"]],"corn":[["2","12"]],"wine":[["2","12"]],"wounded":[["2","12"]],"breathed":[["2","12"]],"bosoms":[["2","12"]],"what":[["2","13"],["2","13"],["2","13"],["5","1"]],"compare":[["2","13"]],"or":[["2","13"]],"liken":[["2","13"]],"equal":[["2","13"]],"may":[["2","13"],["3","7"],["3","29"],["3","44"]],"great":[["2","13"],["3","23"]],"sea":[["2","13"],["4","3"]],"who":[["2","13"],["3","37"]],"heal":[["2","13"]],"false":[["2","14"],["2","14"]],"foolish":[["2","14"]],"laid":[["2","14"],["3","53"]],"open":[["2","14"]],"iniquity":[["2","14"],["3","59"],["4","6"],["4","22"],["4","22"]],"excite":[["2","14"]],"penance":[["2","14"]],"revelations":[["2","14"]],"banishments":[["2","14"]],"passed":[["2","15"]],"clapped":[["2","15"]],"hissed":[["2","15"],["2","16"]],"wagged":[["2","15"]],"saying":[["2","15"]],"this":[["2","15"],["2","16"]],"perfect":[["2","15"]],"joy":[["2","15"],["5","15"]],"opened":[["2","16"],["3","46"]],"gnashed":[["2","16"]],"teeth":[["2","16"],["3","16"]],"we":[["2","16"],["2","16"],["2","16"],["2","16"],["3","22"],["3","42"],["4","17"],["4","17"],["4","20"],["4","20"],["5","3"],["5","4"],["5","4"],["5","5"],["5","5"],["5","6"],["5","6"],["5","7"],["5","9"],["5","16"],["5","21"]],"will":[["2","16"],["3","20"],["3","21"],["3","24"],["3","31"],["3","32"],["4","15"],["4","16"],["4","22"]],"swallow":[["2","16"]],"lo":[["2","16"]],"looked":[["2","16"],["3","50"],["4","17"]],"fulfilled":[["2","17"],["4","18"]],"word":[["2","17"]],"rejoice":[["2","17"],["4","21"]],"over":[["2","17"],["3","21"],["3","53"],["3","54"],["5","8"]],"set":[["2","17"],["3","6"],["3","12"],["3","44"]],"cried":[["2","18"],["4","15"]],"torrent":[["2","18"]],"give":[["2","18"],["2","19"],["3","30"],["3","65"]],"thyself":[["2","18"]],"apple":[["2","18"]],"eye":[["2","18"],["3","48"],["3","49"],["3","51"]],"cease":[["2","18"]],"arise":[["2","19"]],"praise":[["2","19"]],"beginning":[["2","19"],["5","21"]],"watches":[["2","19"]],"pour":[["2","19"]],"lift":[["2","19"],["3","41"]],"life":[["2","19"],["3","53"],["3","58"]],"little":[["2","19"],["4","4"]],"hunger":[["2","19"],["4","9"]],"top":[["2","19"],["4","1"]],"thus":[["2","20"]],"dealt":[["2","20"]],"then":[["2","20"]],"eat":[["2","20"]],"own":[["2","20"],["4","10"]],"fruit":[["2","20"]],"span":[["2","20"]],"prophet":[["2","20"],["4","22"]],"slain":[["2","20"],["2","21"],["4","9"]],"child":[["2","21"],["4","4"]],"man":[["2","21"],["3","1"],["3","27"],["3","35"],["3","36"],["3","39"],["3","39"]],"lie":[["2","21"]],"fallen":[["2","21"],["3","53"],["5","16"]],"shewn":[["2","21"]],"pity":[["2","21"],["4","16"]],"festival":[["2","22"]],"those":[["2","22"],["2","22"],["3","6"]],"terrify":[["2","22"]],"escaped":[["2","22"]],"left":[["2","22"]],"nourished":[["2","22"]],"consumed":[["2","22"],["3","22"],["4","9"]],"poverty":[["3","1"],["3","19"]],"rod":[["3","1"]],"darkness":[["3","2"]],"light":[["3","2"]],"only":[["3","3"]],"again":[["3","3"]],"skin":[["3","4"],["4","8"],["5","10"]],"flesh":[["3","4"]],"built":[["3","5"],["3","7"]],"compassed":[["3","5"]],"gall":[["3","5"],["3","19"]],"labour":[["3","5"],["3","65"]],"dark":[["3","6"]],"places":[["3","6"],["3","10"]],"dead":[["3","6"]],"ever":[["3","6"],["3","31"],["5","19"],["5","20"]],"get":[["3","7"],["4","15"]],"fetters":[["3","7"]],"heavy":[["3","7"]],"yea":[["3","8"]],"cry":[["3","8"]],"entreat":[["3","8"]],"shut":[["3","8"],["3","9"]],"prayer":[["3","8"],["3","44"],["4","22"]],"square":[["3","9"]],"stones":[["3","9"],["4","1"]],"paths":[["3","9"],["3","11"]],"upside":[["3","9"]],"bear":[["3","10"]],"lying":[["3","10"]],"wait":[["3","10"],["3","24"],["3","26"],["4","19"]],"lion":[["3","10"]],"secret":[["3","10"]],"aside":[["3","11"],["3","35"]],"pieces":[["3","11"]],"mark":[["3","12"]],"arrows":[["3","12"]],"shot":[["3","13"]],"reins":[["3","13"]],"daughters":[["3","13"],["3","51"]],"quiver":[["3","13"]],"derision":[["3","14"]],"song":[["3","14"],["3","63"]],"filled":[["3","15"],["3","30"]],"inebriated":[["3","15"]],"wormwood":[["3","15"],["3","19"]],"fed":[["3","16"],["4","5"]],"ashes":[["3","16"]],"good":[["3","17"],["3","25"],["3","26"],["3","27"],["3","38"]],"hope":[["3","18"],["3","21"],["3","25"],["3","29"]],"perished":[["3","18"]],"remember":[["3","19"],["3","20"],["5","1"]],"transgression":[["3","19"]],"mindful":[["3","20"]],"languish":[["3","20"]],"these":[["3","21"],["4","9"]],"think":[["3","21"]],"mercies":[["3","22"],["3","32"]],"commiserations":[["3","22"]],"new":[["3","23"]],"every":[["3","23"],["4","1"]],"morning":[["3","23"]],"faithfulness":[["3","23"]],"portion":[["3","24"]],"seeketh":[["3","25"]],"silence":[["3","26"]],"salvation":[["3","26"]],"god":[["3","26"]],"borne":[["3","27"],["5","7"]],"youth":[["3","27"]],"hold":[["3","28"]],"himself":[["3","28"]],"so":[["3","29"]],"cheek":[["3","30"]],"striketh":[["3","30"]],"reproaches":[["3","30"]],"also":[["3","32"],["4","21"]],"mercy":[["3","32"]],"according":[["3","32"],["3","64"]],"willingly":[["3","33"]],"nor":[["3","33"]],"crush":[["3","34"]],"under":[["3","34"],["3","66"],["4","20"],["5","13"]],"prisoners":[["3","34"]],"land":[["3","34"],["4","21"]],"turn":[["3","35"],["3","56"]],"judgment":[["3","35"],["3","36"],["3","59"]],"most":[["3","35"]],"high":[["3","35"]],"wrongfully":[["3","36"]],"approved":[["3","36"]],"thing":[["3","37"]],"commandeth":[["3","37"]],"proceed":[["3","38"]],"highest":[["3","38"]],"why":[["3","39"],["5","20"],["5","20"]],"living":[["3","39"]],"murmured":[["3","39"]],"suffering":[["3","39"]],"sins":[["3","39"],["4","13"],["4","20"],["4","22"]],"us":[["3","40"],["3","41"],["3","43"],["3","46"],["3","47"],["4","17"],["4","19"],["4","19"],["5","1"],["5","5"],["5","8"],["5","8"],["5","16"],["5","20"],["5","20"],["5","21"],["5","22"],["5","22"]],"search":[["3","40"]],"our":[["3","40"],["3","41"],["3","41"],["3","44"],["3","46"],["4","17"],["4","18"],["4","18"],["4","18"],["4","18"],["4","18"],["4","19"],["4","20"],["4","20"],["5","1"],["5","2"],["5","2"],["5","3"],["5","4"],["5","4"],["5","6"],["5","7"],["5","9"],["5","9"],["5","10"],["5","15"],["5","15"],["5","16"],["5","17"],["5","17"],["5","21"]],"return":[["3","40"]],"hearts":[["3","41"]],"heavens":[["3","41"],["3","50"],["3","66"]],"wickedly":[["3","42"]],"art":[["3","42"],["5","22"]],"inexorable":[["3","42"]],"struck":[["3","43"]],"cloud":[["3","44"]],"through":[["3","44"]],"outcast":[["3","45"]],"refuse":[["3","45"]],"mouths":[["3","46"]],"prophecy":[["3","47"]],"fear":[["3","47"],["3","57"]],"snare":[["3","47"]],"streams":[["3","48"]],"quiet":[["3","49"]],"till":[["3","50"]],"regarded":[["3","50"]],"chased":[["3","52"]],"caught":[["3","52"]],"bird":[["3","52"]],"cause":[["3","52"],["3","58"]],"pit":[["3","53"],["3","55"]],"stone":[["3","53"]],"waters":[["3","54"]],"flowed":[["3","54"]],"head":[["3","54"],["5","16"]],"cut":[["3","54"]],"name":[["3","55"]],"lowest":[["3","55"]],"voice":[["3","56"]],"ear":[["3","56"]],"cries":[["3","56"]],"drewest":[["3","57"]],"near":[["3","57"],["4","18"]],"saidst":[["3","57"]],"judged":[["3","58"]],"redeemer":[["3","58"]],"judge":[["3","59"]],"fury":[["3","60"]],"thoughts":[["3","60"]],"imaginations":[["3","61"]],"lips":[["3","62"]],"devices":[["3","62"]],"sitting":[["3","63"]],"rising":[["3","63"]],"shalt":[["3","64"],["3","65"],["3","66"],["3","66"],["4","21"],["5","19"]],"render":[["3","64"]],"recompense":[["3","64"]],"works":[["3","64"]],"buckler":[["3","65"]],"persecute":[["3","66"]],"gold":[["4","1"],["4","2"]],"dim":[["4","1"],["5","17"]],"finest":[["4","1"]],"colour":[["4","1"]],"changed":[["4","1"]],"scattered":[["4","1"]],"street":[["4","1"]],"noble":[["4","2"]],"sons":[["4","2"]],"clothed":[["4","2"]],"best":[["4","2"]],"esteemed":[["4","2"]],"earthen":[["4","2"]],"vessels":[["4","2"]],"work":[["4","2"]],"potter":[["4","2"]],"even":[["4","3"]],"monsters":[["4","3"]],"breast":[["4","3"]],"suck":[["4","3"]],"cruel":[["4","3"]],"ostrich":[["4","3"]],"desert":[["4","3"],["5","9"]],"tongue":[["4","4"]],"sucking":[["4","4"]],"stuck":[["4","4"],["4","8"]],"roof":[["4","4"]],"thirst":[["4","4"]],"ones":[["4","4"]],"asked":[["4","4"]],"break":[["4","4"]],"delicately":[["4","5"]],"died":[["4","5"],["4","9"]],"scarlet":[["4","5"]],"embraced":[["4","5"]],"dung":[["4","5"]],"greater":[["4","6"]],"than":[["4","6"],["4","7"],["4","7"],["4","7"],["4","7"],["4","8"],["4","9"],["4","19"]],"sodom":[["4","6"]],"moment":[["4","6"]],"took":[["4","6"]],"nothing":[["4","6"]],"nazarites":[["4","7"]],"whiter":[["4","7"]],"snow":[["4","7"]],"purer":[["4","7"]],"milk":[["4","7"]],"ruddy":[["4","7"]],"ivory":[["4","7"]],"fairer":[["4","7"]],"sapphire":[["4","7"]],"now":[["4","8"]],"blacker":[["4","8"]],"coals":[["4","8"]],"known":[["4","8"]],"withered":[["4","8"]],"wood":[["4","8"],["5","4"],["5","13"]],"better":[["4","9"]],"being":[["4","9"],["4","15"]],"want":[["4","9"]],"fruits":[["4","9"]],"pitiful":[["4","10"]],"sodden":[["4","10"]],"meat":[["4","10"]],"accomplished":[["4","11"],["4","22"]],"devoured":[["4","11"]],"foundations":[["4","11"]],"kings":[["4","12"]],"inhabitants":[["4","12"]],"world":[["4","12"]],"would":[["4","12"]],"believed":[["4","12"]],"shed":[["4","13"]],"blood":[["4","13"],["4","14"]],"wandered":[["4","14"]],"blind":[["4","14"]],"defiled":[["4","14"],["4","15"]],"could":[["4","14"]],"help":[["4","14"],["4","17"]],"walking":[["4","14"]],"skirts":[["4","14"]],"depart":[["4","15"],["4","15"]],"hence":[["4","15"]],"touch":[["4","15"]],"quarrelled":[["4","15"]],"dwell":[["4","15"]],"divided":[["4","16"]],"regard":[["4","16"]],"respected":[["4","16"]],"persons":[["4","16"],["5","12"]],"neither":[["4","16"]],"ancient":[["4","16"],["5","12"]],"yet":[["4","17"]],"standing":[["4","17"]],"expecting":[["4","17"]],"vain":[["4","17"]],"attentively":[["4","17"]],"towards":[["4","17"]],"nation":[["4","17"]],"save":[["4","17"]],"steps":[["4","18"]],"slipped":[["4","18"]],"draweth":[["4","18"]],"swifter":[["4","19"]],"eagles":[["4","19"]],"air":[["4","19"]],"pursued":[["4","19"]],"mountains":[["4","19"]],"lay":[["4","19"]],"wilderness":[["4","19"]],"breath":[["4","20"]],"christ":[["4","20"]],"shadow":[["4","20"]],"live":[["4","20"]],"glad":[["4","21"]],"edom":[["4","21"],["4","22"]],"dwellest":[["4","21"]],"hus":[["4","21"]],"cup":[["4","21"]],"drunk":[["4","21"],["5","4"]],"naked":[["4","21"]],"carry":[["4","22"]],"visited":[["4","22"]],"discovered":[["4","22"]],"jeremias":[["4","22"]],"inheritance":[["5","2"]],"aliens":[["5","2"]],"houses":[["5","2"]],"strangers":[["5","2"]],"orphans":[["5","3"]],"father":[["5","3"]],"widows":[["5","3"]],"money":[["5","4"]],"bought":[["5","4"]],"dragged":[["5","5"]],"necks":[["5","5"]],"weary":[["5","5"]],"egypt":[["5","6"]],"assyrians":[["5","6"]],"might":[["5","6"]],"satisfied":[["5","6"]],"fathers":[["5","7"]],"servants":[["5","8"]],"ruled":[["5","8"]],"redeem":[["5","8"]],"fetched":[["5","9"]],"peril":[["5","9"]],"lives":[["5","9"]],"burnt":[["5","10"]],"oven":[["5","10"]],"reason":[["5","10"]],"violence":[["5","10"]],"famine":[["5","10"]],"cities":[["5","11"]],"hanged":[["5","12"]],"did":[["5","12"]],"respect":[["5","12"]],"abused":[["5","13"]],"indecently":[["5","13"]],"ceased":[["5","14"],["5","15"]],"choir":[["5","14"]],"singers":[["5","14"]],"dancing":[["5","15"]],"mourning":[["5","15"]],"crown":[["5","16"]],"woe":[["5","16"]],"mount":[["5","18"]],"foxes":[["5","18"]],"walked":[["5","18"]],"remain":[["5","19"]],"throne":[["5","19"]],"generation":[["5","19"],["5","19"]],"wilt":[["5","20"],["5","20"]],"forget":[["5","20"]],"forsake":[["5","20"]],"convert":[["5","21"]],"converted":[["5","21"]],"renew":[["5","21"]],"utterly":[["5","22"]],"rejected":[["5","22"]],"exceedingly":[["5","22"]],"angry":[["5","22"]]}}