{"book":{"id":"colossians","name":"Colossians","osis":"Col"},"chapters":{"1":{"1":[{"match":"direct","source_href":"../../ellicott/colossians/1.htm","source_id":"ellicott","source_name":"Ellicott's Commentary for English Readers","source_ref":{"book_id":"colossians","chapter":1,"entry_index":0,"source_chapter":1,"verse":1}},{"match":"direct","source_href":"../../pulpit/colossians/1.htm","source_id":"pulpit","source_name":"Pulpit Commentary","source_ref":{"book_id":"colossians","chapter":1,"entry_index":0,"source_chapter":1,"verse":1}},{"match":"direct","source_href":"../../mhc/colossians/1.htm","source_id":"mhc","source_name":"Matthew Henry's Concise Commentary","source_ref":{"book_id":"colossians","chapter":1,"entry_index":0,"source_chapter":1,"verse":1}},{"match":"direct","source_href":"../../gill/colossians/1.htm","source_id":"gill","source_name":"Gill's Exposition of the Entire Bible","source_ref":{"book_id":"colossians","chapter":1,"entry_index":0,"source_chapter":1,"verse":1}}],"10":[{"match":"direct","source_href":"../../ellicott/colossians/1.htm","source_id":"ellicott","source_name":"Ellicott's Commentary for English Readers","source_ref":{"book_id":"colossians","chapter":1,"entry_index":0,"source_chapter":1,"verse":10}},{"match":"direct","source_href":"../../pulpit/colossians/1.htm","source_id":"pulpit","source_name":"Pulpit Commentary","source_ref":{"book_id":"colossians","chapter":1,"entry_index":0,"source_chapter":1,"verse":10}},{"match":"hash","source_href":"../../mhc/colossians/1.htm","source_id":"mhc","source_name":"Matthew Henry's Concise Commentary","source_ref":{"book_id":"colossians","chapter":1,"entry_index":0,"source_chapter":1,"verse":9},"text_hash":"a379663c5ceafbb6407b87b41c5afb13a8e777c9"},{"match":"direct","source_href":"../../gill/colossians/1.htm","source_id":"gill","source_name":"Gill's Exposition of the Entire Bible","source_ref":{"book_id":"colossians","chapter":1,"entry_index":0,"source_chapter":1,"verse":10}}],"11":[{"match":"direct","source_href":"../../ellicott/colossians/1.htm","source_id":"ellicott","source_name":"Ellicott's Commentary for English Readers","source_ref":{"book_id":"colossians","chapter":1,"entry_index":0,"source_chapter":1,"verse":11}},{"match":"direct","source_href":"../../pulpit/colossians/1.htm","source_id":"pulpit","source_name":"Pulpit Commentary","source_ref":{"book_id":"colossians","chapter":1,"entry_index":0,"source_chapter":1,"verse":11}},{"match":"hash","source_href":"../../mhc/colossians/1.htm","source_id":"mhc","source_name":"Matthew Henry's Concise Commentary","source_ref":{"book_id":"colossians","chapter":1,"entry_index":0,"source_chapter":1,"verse":9},"text_hash":"a379663c5ceafbb6407b87b41c5afb13a8e777c9"},{"match":"direct","source_href":"../../gill/colossians/1.htm","source_id":"gill","source_name":"Gill's Exposition of the Entire Bible","source_ref":{"book_id":"colossians","chapter":1,"entry_index":0,"source_chapter":1,"verse":11}}],"12":[{"match":"direct","source_href":"../../ellicott/colossians/1.htm","source_id":"ellicott","source_name":"Ellicott's Commentary for English Readers","source_ref":{"book_id":"colossians","chapter":1,"entry_index":0,"source_chapter":1,"verse":12}},{"match":"direct","source_href":"../../pulpit/colossians/1.htm","source_id":"pulpit","source_name":"Pulpit Commentary","source_ref":{"book_id":"colossians","chapter":1,"entry_index":0,"source_chapter":1,"verse":12}},{"match":"hash","source_href":"../../mhc/colossians/1.htm","source_id":"mhc","source_name":"Matthew Henry's Concise Commentary","source_ref":{"book_id":"colossians","chapter":1,"entry_index":0,"source_chapter":1,"verse":9},"text_hash":"a379663c5ceafbb6407b87b41c5afb13a8e777c9"},{"match":"direct","source_href":"../../gill/colossians/1.htm","source_id":"gill","source_name":"Gill's Exposition of the Entire Bible","source_ref":{"book_id":"colossians","chapter":1,"entry_index":0,"source_chapter":1,"verse":12}}],"13":[{"match":"direct","source_href":"../../ellicott/colossians/1.htm","source_id":"ellicott","source_name":"Ellicott's Commentary for English Readers","source_ref":{"book_id":"colossians","chapter":1,"entry_index":0,"source_chapter":1,"verse":13}},{"match":"direct","source_href":"../../pulpit/colossians/1.htm","source_id":"pulpit","source_name":"Pulpit Commentary","source_ref":{"book_id":"colossians","chapter":1,"entry_index":0,"source_chapter":1,"verse":13}},{"match":"hash","source_href":"../../mhc/colossians/1.htm","source_id":"mhc","source_name":"Matthew Henry's Concise Commentary","source_ref":{"book_id":"colossians","chapter":1,"entry_index":0,"source_chapter":1,"verse":9},"text_hash":"a379663c5ceafbb6407b87b41c5afb13a8e777c9"},{"match":"direct","source_href":"../../gill/colossians/1.htm","source_id":"gill","source_name":"Gill's Exposition of the Entire Bible","source_ref":{"book_id":"colossians","chapter":1,"entry_index":0,"source_chapter":1,"verse":13}}],"14":[{"match":"direct","source_href":"../../pulpit/colossians/1.htm","source_id":"pulpit","source_name":"Pulpit Commentary","source_ref":{"book_id":"colossians","chapter":1,"entry_index":0,"source_chapter":1,"verse":14}},{"match":"hash","source_href":"../../mhc/colossians/1.htm","source_id":"mhc","source_name":"Matthew Henry's Concise Commentary","source_ref":{"book_id":"colossians","chapter":1,"entry_index":0,"source_chapter":1,"verse":9},"text_hash":"a379663c5ceafbb6407b87b41c5afb13a8e777c9"},{"match":"direct","source_href":"../../gill/colossians/1.htm","source_id":"gill","source_name":"Gill's Exposition of the Entire Bible","source_ref":{"book_id":"colossians","chapter":1,"entry_index":0,"source_chapter":1,"verse":14}}],"15":[{"match":"direct","source_href":"../../ellicott/colossians/1.htm","source_id":"ellicott","source_name":"Ellicott's Commentary for English Readers","source_ref":{"book_id":"colossians","chapter":1,"entry_index":0,"source_chapter":1,"verse":15}},{"match":"direct","source_href":"../../pulpit/colossians/1.htm","source_id":"pulpit","source_name":"Pulpit Commentary","source_ref":{"book_id":"colossians","chapter":1,"entry_index":0,"source_chapter":1,"verse":15}},{"match":"direct","source_href":"../../mhc/colossians/1.htm","source_id":"mhc","source_name":"Matthew Henry's Concise Commentary","source_ref":{"book_id":"colossians","chapter":1,"entry_index":0,"source_chapter":1,"verse":15}},{"match":"direct","source_href":"../../gill/colossians/1.htm","source_id":"gill","source_name":"Gill's Exposition of the Entire Bible","source_ref":{"book_id":"colossians","chapter":1,"entry_index":0,"source_chapter":1,"verse":15}}],"16":[{"match":"direct","source_href":"../../ellicott/colossians/1.htm","source_id":"ellicott","source_name":"Ellicott's Commentary for English Readers","source_ref":{"book_id":"colossians","chapter":1,"entry_index":0,"source_chapter":1,"verse":16}},{"match":"direct","source_href":"../../pulpit/colossians/1.htm","source_id":"pulpit","source_name":"Pulpit Commentary","source_ref":{"book_id":"colossians","chapter":1,"entry_index":0,"source_chapter":1,"verse":16}},{"match":"hash","source_href":"../../mhc/colossians/1.htm","source_id":"mhc","source_name":"Matthew Henry's Concise Commentary","source_ref":{"book_id":"colossians","chapter":1,"entry_index":0,"source_chapter":1,"verse":15},"text_hash":"25fa93a288ae754c1d5437e8e582b19009918ea6"},{"match":"direct","source_href":"../../gill/colossians/1.htm","source_id":"gill","source_name":"Gill's Exposition of the Entire Bible","source_ref":{"book_id":"colossians","chapter":1,"entry_index":0,"source_chapter":1,"verse":16}}],"17":[{"match":"direct","source_href":"../../ellicott/colossians/1.htm","source_id":"ellicott","source_name":"Ellicott's Commentary for English Readers","source_ref":{"book_id":"colossians","chapter":1,"entry_index":0,"source_chapter":1,"verse":17}},{"match":"direct","source_href":"../../pulpit/colossians/1.htm","source_id":"pulpit","source_name":"Pulpit Commentary","source_ref":{"book_id":"colossians","chapter":1,"entry_index":0,"source_chapter":1,"verse":17}},{"match":"hash","source_href":"../../mhc/colossians/1.htm","source_id":"mhc","source_name":"Matthew Henry's Concise Commentary","source_ref":{"book_id":"colossians","chapter":1,"entry_index":0,"source_chapter":1,"verse":15},"text_hash":"25fa93a288ae754c1d5437e8e582b19009918ea6"},{"match":"direct","source_href":"../../gill/colossians/1.htm","source_id":"gill","source_name":"Gill's Exposition of the Entire Bible","source_ref":{"book_id":"colossians","chapter":1,"entry_index":0,"source_chapter":1,"verse":17}}],"18":[{"match":"direct","source_href":"../../ellicott/colossians/1.htm","source_id":"ellicott","source_name":"Ellicott's Commentary for English Readers","source_ref":{"book_id":"colossians","chapter":1,"entry_index":0,"source_chapter":1,"verse":18}},{"match":"direct","source_href":"../../pulpit/colossians/1.htm","source_id":"pulpit","source_name":"Pulpit Commentary","source_ref":{"book_id":"colossians","chapter":1,"entry_index":0,"source_chapter":1,"verse":18}},{"match":"hash","source_href":"../../mhc/colossians/1.htm","source_id":"mhc","source_name":"Matthew Henry's Concise Commentary","source_ref":{"book_id":"colossians","chapter":1,"entry_index":0,"source_chapter":1,"verse":15},"text_hash":"25fa93a288ae754c1d5437e8e582b19009918ea6"},{"match":"direct","source_href":"../../gill/colossians/1.htm","source_id":"gill","source_name":"Gill's Exposition of the Entire Bible","source_ref":{"book_id":"colossians","chapter":1,"entry_index":0,"source_chapter":1,"verse":18}}],"19":[{"match":"direct","source_href":"../../ellicott/colossians/1.htm","source_id":"ellicott","source_name":"Ellicott's Commentary for English Readers","source_ref":{"book_id":"colossians","chapter":1,"entry_index":0,"source_chapter":1,"verse":19}},{"match":"direct","source_href":"../../pulpit/colossians/1.htm","source_id":"pulpit","source_name":"Pulpit Commentary","source_ref":{"book_id":"colossians","chapter":1,"entry_index":0,"source_chapter":1,"verse":19}},{"match":"hash","source_href":"../../mhc/colossians/1.htm","source_id":"mhc","source_name":"Matthew Henry's Concise Commentary","source_ref":{"book_id":"colossians","chapter":1,"entry_index":0,"source_chapter":1,"verse":15},"text_hash":"25fa93a288ae754c1d5437e8e582b19009918ea6"},{"match":"direct","source_href":"../../gill/colossians/1.htm","source_id":"gill","source_name":"Gill's Exposition of the Entire Bible","source_ref":{"book_id":"colossians","chapter":1,"entry_index":0,"source_chapter":1,"verse":19}}],"2":[{"match":"direct","source_href":"../../ellicott/colossians/1.htm","source_id":"ellicott","source_name":"Ellicott's Commentary for English Readers","source_ref":{"book_id":"colossians","chapter":1,"entry_index":0,"source_chapter":1,"verse":2}},{"match":"direct","source_href":"../../pulpit/colossians/1.htm","source_id":"pulpit","source_name":"Pulpit Commentary","source_ref":{"book_id":"colossians","chapter":1,"entry_index":0,"source_chapter":1,"verse":2}},{"match":"hash","source_href":"../../mhc/colossians/1.htm","source_id":"mhc","source_name":"Matthew Henry's Concise Commentary","source_ref":{"book_id":"colossians","chapter":1,"entry_index":0,"source_chapter":1,"verse":1},"text_hash":"50dd8339c44ad29e61cdb2a3d29ceb3213d84316"},{"match":"direct","source_href":"../../gill/colossians/1.htm","source_id":"gill","source_name":"Gill's Exposition of the Entire Bible","source_ref":{"book_id":"colossians","chapter":1,"entry_index":0,"source_chapter":1,"verse":2}}],"20":[{"match":"direct","source_href":"../../ellicott/colossians/1.htm","source_id":"ellicott","source_name":"Ellicott's Commentary for English Readers","source_ref":{"book_id":"colossians","chapter":1,"entry_index":0,"source_chapter":1,"verse":20}},{"match":"direct","source_href":"../../pulpit/colossians/1.htm","source_id":"pulpit","source_name":"Pulpit Commentary","source_ref":{"book_id":"colossians","chapter":1,"entry_index":0,"source_chapter":1,"verse":20}},{"match":"hash","source_href":"../../mhc/colossians/1.htm","source_id":"mhc","source_name":"Matthew Henry's Concise Commentary","source_ref":{"book_id":"colossians","chapter":1,"entry_index":0,"source_chapter":1,"verse":15},"text_hash":"25fa93a288ae754c1d5437e8e582b19009918ea6"},{"match":"direct","source_href":"../../gill/colossians/1.htm","source_id":"gill","source_name":"Gill's Exposition of the Entire Bible","source_ref":{"book_id":"colossians","chapter":1,"entry_index":0,"source_chapter":1,"verse":20}}],"21":[{"match":"direct","source_href":"../../ellicott/colossians/1.htm","source_id":"ellicott","source_name":"Ellicott's Commentary for English Readers","source_ref":{"book_id":"colossians","chapter":1,"entry_index":0,"source_chapter":1,"verse":21}},{"match":"direct","source_href":"../../pulpit/colossians/1.htm","source_id":"pulpit","source_name":"Pulpit Commentary","source_ref":{"book_id":"colossians","chapter":1,"entry_index":0,"source_chapter":1,"verse":21}},{"match":"hash","source_href":"../../mhc/colossians/1.htm","source_id":"mhc","source_name":"Matthew Henry's Concise Commentary","source_ref":{"book_id":"colossians","chapter":1,"entry_index":0,"source_chapter":1,"verse":15},"text_hash":"25fa93a288ae754c1d5437e8e582b19009918ea6"},{"match":"direct","source_href":"../../gill/colossians/1.htm","source_id":"gill","source_name":"Gill's Exposition of the Entire Bible","source_ref":{"book_id":"colossians","chapter":1,"entry_index":0,"source_chapter":1,"verse":21}}],"22":[{"match":"direct","source_href":"../../ellicott/colossians/1.htm","source_id":"ellicott","source_name":"Ellicott's Commentary for English Readers","source_ref":{"book_id":"colossians","chapter":1,"entry_index":0,"source_chapter":1,"verse":22}},{"match":"direct","source_href":"../../pulpit/colossians/1.htm","source_id":"pulpit","source_name":"Pulpit Commentary","source_ref":{"book_id":"colossians","chapter":1,"entry_index":0,"source_chapter":1,"verse":22}},{"match":"hash","source_href":"../../mhc/colossians/1.htm","source_id":"mhc","source_name":"Matthew Henry's Concise Commentary","source_ref":{"book_id":"colossians","chapter":1,"entry_index":0,"source_chapter":1,"verse":15},"text_hash":"25fa93a288ae754c1d5437e8e582b19009918ea6"},{"match":"direct","source_href":"../../gill/colossians/1.htm","source_id":"gill","source_name":"Gill's Exposition of the Entire Bible","source_ref":{"book_id":"colossians","chapter":1,"entry_index":0,"source_chapter":1,"verse":22}}],"23":[{"match":"direct","source_href":"../../ellicott/colossians/1.htm","source_id":"ellicott","source_name":"Ellicott's Commentary for English Readers","source_ref":{"book_id":"colossians","chapter":1,"entry_index":0,"source_chapter":1,"verse":23}},{"match":"direct","source_href":"../../pulpit/colossians/1.htm","source_id":"pulpit","source_name":"Pulpit Commentary","source_ref":{"book_id":"colossians","chapter":1,"entry_index":0,"source_chapter":1,"verse":23}},{"match":"hash","source_href":"../../mhc/colossians/1.htm","source_id":"mhc","source_name":"Matthew Henry's Concise Commentary","source_ref":{"book_id":"colossians","chapter":1,"entry_index":0,"source_chapter":1,"verse":15},"text_hash":"25fa93a288ae754c1d5437e8e582b19009918ea6"},{"match":"direct","source_href":"../../gill/colossians/1.htm","source_id":"gill","source_name":"Gill's Exposition of the Entire Bible","source_ref":{"book_id":"colossians","chapter":1,"entry_index":0,"source_chapter":1,"verse":23}}],"24":[{"match":"direct","source_href":"../../ellicott/colossians/1.htm","source_id":"ellicott","source_name":"Ellicott's Commentary for English Readers","source_ref":{"book_id":"colossians","chapter":1,"entry_index":0,"source_chapter":1,"verse":24}},{"match":"direct","source_href":"../../pulpit/colossians/1.htm","source_id":"pulpit","source_name":"Pulpit Commentary","source_ref":{"book_id":"colossians","chapter":1,"entry_index":0,"source_chapter":1,"verse":24}},{"match":"direct","source_href":"../../mhc/colossians/1.htm","source_id":"mhc","source_name":"Matthew Henry's Concise Commentary","source_ref":{"book_id":"colossians","chapter":1,"entry_index":0,"source_chapter":1,"verse":24}},{"match":"direct","source_href":"../../gill/colossians/1.htm","source_id":"gill","source_name":"Gill's Exposition of the Entire Bible","source_ref":{"book_id":"colossians","chapter":1,"entry_index":0,"source_chapter":1,"verse":24}}],"25":[{"match":"direct","source_href":"../../ellicott/colossians/1.htm","source_id":"ellicott","source_name":"Ellicott's Commentary for English Readers","source_ref":{"book_id":"colossians","chapter":1,"entry_index":0,"source_chapter":1,"verse":25}},{"match":"direct","source_href":"../../pulpit/colossians/1.htm","source_id":"pulpit","source_name":"Pulpit Commentary","source_ref":{"book_id":"colossians","chapter":1,"entry_index":0,"source_chapter":1,"verse":25}},{"match":"hash","source_href":"../../mhc/colossians/1.htm","source_id":"mhc","source_name":"Matthew Henry's Concise Commentary","source_ref":{"book_id":"colossians","chapter":1,"entry_index":0,"source_chapter":1,"verse":24},"text_hash":"30ac7882c73412968da682b92330d28b20263423"},{"match":"direct","source_href":"../../gill/colossians/1.htm","source_id":"gill","source_name":"Gill's Exposition of the Entire Bible","source_ref":{"book_id":"colossians","chapter":1,"entry_index":0,"source_chapter":1,"verse":25}}],"26":[{"match":"direct","source_href":"../../ellicott/colossians/1.htm","source_id":"ellicott","source_name":"Ellicott's Commentary for English Readers","source_ref":{"book_id":"colossians","chapter":1,"entry_index":0,"source_chapter":1,"verse":26}},{"match":"direct","source_href":"../../pulpit/colossians/1.htm","source_id":"pulpit","source_name":"Pulpit Commentary","source_ref":{"book_id":"colossians","chapter":1,"entry_index":0,"source_chapter":1,"verse":26}},{"match":"hash","source_href":"../../mhc/colossians/1.htm","source_id":"mhc","source_name":"Matthew Henry's Concise Commentary","source_ref":{"book_id":"colossians","chapter":1,"entry_index":0,"source_chapter":1,"verse":24},"text_hash":"30ac7882c73412968da682b92330d28b20263423"},{"match":"direct","source_href":"../../gill/colossians/1.htm","source_id":"gill","source_name":"Gill's Exposition of the Entire Bible","source_ref":{"book_id":"colossians","chapter":1,"entry_index":0,"source_chapter":1,"verse":26}}],"27":[{"match":"direct","source_href":"../../ellicott/colossians/1.htm","source_id":"ellicott","source_name":"Ellicott's Commentary for English Readers","source_ref":{"book_id":"colossians","chapter":1,"entry_index":0,"source_chapter":1,"verse":27}},{"match":"direct","source_href":"../../pulpit/colossians/1.htm","source_id":"pulpit","source_name":"Pulpit Commentary","source_ref":{"book_id":"colossians","chapter":1,"entry_index":0,"source_chapter":1,"verse":27}},{"match":"hash","source_href":"../../mhc/colossians/1.htm","source_id":"mhc","source_name":"Matthew Henry's Concise Commentary","source_ref":{"book_id":"colossians","chapter":1,"entry_index":0,"source_chapter":1,"verse":24},"text_hash":"30ac7882c73412968da682b92330d28b20263423"},{"match":"direct","source_href":"../../gill/colossians/1.htm","source_id":"gill","source_name":"Gill's Exposition of the Entire Bible","source_ref":{"book_id":"colossians","chapter":1,"entry_index":0,"source_chapter":1,"verse":27}}],"28":[{"match":"direct","source_href":"../../ellicott/colossians/1.htm","source_id":"ellicott","source_name":"Ellicott's Commentary for English Readers","source_ref":{"book_id":"colossians","chapter":1,"entry_index":0,"source_chapter":1,"verse":28}},{"match":"direct","source_href":"../../pulpit/colossians/1.htm","source_id":"pulpit","source_name":"Pulpit Commentary","source_ref":{"book_id":"colossians","chapter":1,"entry_index":0,"source_chapter":1,"verse":28}},{"match":"hash","source_href":"../../mhc/colossians/1.htm","source_id":"mhc","source_name":"Matthew Henry's Concise Commentary","source_ref":{"book_id":"colossians","chapter":1,"entry_index":0,"source_chapter":1,"verse":24},"text_hash":"30ac7882c73412968da682b92330d28b20263423"},{"match":"direct","source_href":"../../gill/colossians/1.htm","source_id":"gill","source_name":"Gill's Exposition of the Entire Bible","source_ref":{"book_id":"colossians","chapter":1,"entry_index":0,"source_chapter":1,"verse":28}}],"29":[{"match":"direct","source_href":"../../ellicott/colossians/1.htm","source_id":"ellicott","source_name":"Ellicott's Commentary for English Readers","source_ref":{"book_id":"colossians","chapter":1,"entry_index":0,"source_chapter":1,"verse":29}},{"match":"direct","source_href":"../../pulpit/colossians/1.htm","source_id":"pulpit","source_name":"Pulpit Commentary","source_ref":{"book_id":"colossians","chapter":1,"entry_index":0,"source_chapter":1,"verse":29}},{"match":"hash","source_href":"../../mhc/colossians/1.htm","source_id":"mhc","source_name":"Matthew Henry's Concise Commentary","source_ref":{"book_id":"colossians","chapter":1,"entry_index":0,"source_chapter":1,"verse":24},"text_hash":"30ac7882c73412968da682b92330d28b20263423"},{"match":"direct","source_href":"../../gill/colossians/1.htm","source_id":"gill","source_name":"Gill's Exposition of the Entire Bible","source_ref":{"book_id":"colossians","chapter":1,"entry_index":0,"source_chapter":2,"verse":29}}],"3":[{"match":"direct","source_href":"../../ellicott/colossians/1.htm","source_id":"ellicott","source_name":"Ellicott's Commentary for English Readers","source_ref":{"book_id":"colossians","chapter":1,"entry_index":0,"source_chapter":1,"verse":3}},{"match":"direct","source_href":"../../pulpit/colossians/1.htm","source_id":"pulpit","source_name":"Pulpit Commentary","source_ref":{"book_id":"colossians","chapter":1,"entry_index":0,"source_chapter":1,"verse":3}},{"match":"hash","source_href":"../../mhc/colossians/1.htm","source_id":"mhc","source_name":"Matthew Henry's Concise Commentary","source_ref":{"book_id":"colossians","chapter":1,"entry_index":0,"source_chapter":1,"verse":1},"text_hash":"50dd8339c44ad29e61cdb2a3d29ceb3213d84316"},{"match":"direct","source_href":"../../gill/colossians/1.htm","source_id":"gill","source_name":"Gill's Exposition of the Entire Bible","source_ref":{"book_id":"colossians","chapter":1,"entry_index":0,"source_chapter":1,"verse":3}}],"4":[{"match":"direct","source_href":"../../pulpit/colossians/1.htm","source_id":"pulpit","source_name":"Pulpit Commentary","source_ref":{"book_id":"colossians","chapter":1,"entry_index":0,"source_chapter":1,"verse":4}},{"match":"hash","source_href":"../../mhc/colossians/1.htm","source_id":"mhc","source_name":"Matthew Henry's Concise Commentary","source_ref":{"book_id":"colossians","chapter":1,"entry_index":0,"source_chapter":1,"verse":1},"text_hash":"50dd8339c44ad29e61cdb2a3d29ceb3213d84316"},{"match":"direct","source_href":"../../gill/colossians/1.htm","source_id":"gill","source_name":"Gill's Exposition of the Entire Bible","source_ref":{"book_id":"colossians","chapter":1,"entry_index":0,"source_chapter":1,"verse":4}}],"5":[{"match":"direct","source_href":"../../ellicott/colossians/1.htm","source_id":"ellicott","source_name":"Ellicott's Commentary for English Readers","source_ref":{"book_id":"colossians","chapter":1,"entry_index":0,"source_chapter":1,"verse":5}},{"match":"direct","source_href":"../../pulpit/colossians/1.htm","source_id":"pulpit","source_name":"Pulpit Commentary","source_ref":{"book_id":"colossians","chapter":1,"entry_index":0,"source_chapter":1,"verse":5}},{"match":"hash","source_href":"../../mhc/colossians/1.htm","source_id":"mhc","source_name":"Matthew Henry's Concise Commentary","source_ref":{"book_id":"colossians","chapter":1,"entry_index":0,"source_chapter":1,"verse":1},"text_hash":"50dd8339c44ad29e61cdb2a3d29ceb3213d84316"},{"match":"direct","source_href":"../../gill/colossians/1.htm","source_id":"gill","source_name":"Gill's Exposition of the Entire Bible","source_ref":{"book_id":"colossians","chapter":1,"entry_index":0,"source_chapter":1,"verse":5}}],"6":[{"match":"direct","source_href":"../../ellicott/colossians/1.htm","source_id":"ellicott","source_name":"Ellicott's Commentary for English Readers","source_ref":{"book_id":"colossians","chapter":1,"entry_index":0,"source_chapter":1,"verse":6}},{"match":"direct","source_href":"../../pulpit/colossians/1.htm","source_id":"pulpit","source_name":"Pulpit Commentary","source_ref":{"book_id":"colossians","chapter":1,"entry_index":0,"source_chapter":1,"verse":6}},{"match":"hash","source_href":"../../mhc/colossians/1.htm","source_id":"mhc","source_name":"Matthew Henry's Concise Commentary","source_ref":{"book_id":"colossians","chapter":1,"entry_index":0,"source_chapter":1,"verse":1},"text_hash":"50dd8339c44ad29e61cdb2a3d29ceb3213d84316"},{"match":"direct","source_href":"../../gill/colossians/1.htm","source_id":"gill","source_name":"Gill's Exposition of the Entire Bible","source_ref":{"book_id":"colossians","chapter":1,"entry_index":0,"source_chapter":1,"verse":6}}],"7":[{"match":"direct","source_href":"../../ellicott/colossians/1.htm","source_id":"ellicott","source_name":"Ellicott's Commentary for English Readers","source_ref":{"book_id":"colossians","chapter":1,"entry_index":0,"source_chapter":1,"verse":7}},{"match":"direct","source_href":"../../pulpit/colossians/1.htm","source_id":"pulpit","source_name":"Pulpit Commentary","source_ref":{"book_id":"colossians","chapter":1,"entry_index":0,"source_chapter":1,"verse":7}},{"match":"hash","source_href":"../../mhc/colossians/1.htm","source_id":"mhc","source_name":"Matthew Henry's Concise Commentary","source_ref":{"book_id":"colossians","chapter":1,"entry_index":0,"source_chapter":1,"verse":1},"text_hash":"50dd8339c44ad29e61cdb2a3d29ceb3213d84316"},{"match":"direct","source_href":"../../gill/colossians/1.htm","source_id":"gill","source_name":"Gill's Exposition of the Entire Bible","source_ref":{"book_id":"colossians","chapter":1,"entry_index":0,"source_chapter":1,"verse":7}}],"8":[{"match":"direct","source_href":"../../ellicott/colossians/1.htm","source_id":"ellicott","source_name":"Ellicott's Commentary for English Readers","source_ref":{"book_id":"colossians","chapter":1,"entry_index":0,"source_chapter":1,"verse":8}},{"match":"direct","source_href":"../../pulpit/colossians/1.htm","source_id":"pulpit","source_name":"Pulpit Commentary","source_ref":{"book_id":"colossians","chapter":1,"entry_index":0,"source_chapter":1,"verse":8}},{"match":"hash","source_href":"../../mhc/colossians/1.htm","source_id":"mhc","source_name":"Matthew Henry's Concise Commentary","source_ref":{"book_id":"colossians","chapter":1,"entry_index":0,"source_chapter":1,"verse":1},"text_hash":"50dd8339c44ad29e61cdb2a3d29ceb3213d84316"},{"match":"direct","source_href":"../../gill/colossians/1.htm","source_id":"gill","source_name":"Gill's Exposition of the Entire Bible","source_ref":{"book_id":"colossians","chapter":1,"entry_index":0,"source_chapter":1,"verse":8}}],"9":[{"match":"direct","source_href":"../../ellicott/colossians/1.htm","source_id":"ellicott","source_name":"Ellicott's Commentary for English Readers","source_ref":{"book_id":"colossians","chapter":1,"entry_index":0,"source_chapter":1,"verse":9}},{"match":"direct","source_href":"../../pulpit/colossians/1.htm","source_id":"pulpit","source_name":"Pulpit Commentary","source_ref":{"book_id":"colossians","chapter":1,"entry_index":0,"source_chapter":1,"verse":9}},{"match":"direct","source_href":"../../mhc/colossians/1.htm","source_id":"mhc","source_name":"Matthew Henry's Concise Commentary","source_ref":{"book_id":"colossians","chapter":1,"entry_index":0,"source_chapter":1,"verse":9}},{"match":"direct","source_href":"../../gill/colossians/1.htm","source_id":"gill","source_name":"Gill's Exposition of the Entire Bible","source_ref":{"book_id":"colossians","chapter":1,"entry_index":0,"source_chapter":1,"verse":9}}]},"2":{"1":[{"match":"direct","source_href":"../../ellicott/colossians/2.htm","source_id":"ellicott","source_name":"Ellicott's Commentary for English Readers","source_ref":{"book_id":"colossians","chapter":2,"entry_index":0,"source_chapter":2,"verse":1}},{"match":"direct","source_href":"../../pulpit/colossians/2.htm","source_id":"pulpit","source_name":"Pulpit Commentary","source_ref":{"book_id":"colossians","chapter":2,"entry_index":0,"source_chapter":2,"verse":1}},{"match":"direct","source_href":"../../mhc/colossians/2.htm","source_id":"mhc","source_name":"Matthew Henry's Concise Commentary","source_ref":{"book_id":"colossians","chapter":2,"entry_index":0,"source_chapter":2,"verse":1}},{"match":"direct","source_href":"../../gill/colossians/2.htm","source_id":"gill","source_name":"Gill's Exposition of the Entire Bible","source_ref":{"book_id":"colossians","chapter":2,"entry_index":0,"source_chapter":2,"verse":1}}],"10":[{"match":"direct","source_href":"../../ellicott/colossians/2.htm","source_id":"ellicott","source_name":"Ellicott's Commentary for English Readers","source_ref":{"book_id":"colossians","chapter":2,"entry_index":0,"source_chapter":2,"verse":10}},{"match":"direct","source_href":"../../pulpit/colossians/2.htm","source_id":"pulpit","source_name":"Pulpit Commentary","source_ref":{"book_id":"colossians","chapter":2,"entry_index":0,"source_chapter":2,"verse":10}},{"match":"hash","source_href":"../../mhc/colossians/2.htm","source_id":"mhc","source_name":"Matthew Henry's Concise Commentary","source_ref":{"book_id":"colossians","chapter":2,"entry_index":0,"source_chapter":2,"verse":8},"text_hash":"4cdcb637c432623da6d5bc7ef3794e5228551ef5"},{"match":"direct","source_href":"../../gill/colossians/2.htm","source_id":"gill","source_name":"Gill's Exposition of the Entire Bible","source_ref":{"book_id":"colossians","chapter":2,"entry_index":0,"source_chapter":2,"verse":10}}],"11":[{"match":"direct","source_href":"../../ellicott/colossians/2.htm","source_id":"ellicott","source_name":"Ellicott's Commentary for English Readers","source_ref":{"book_id":"colossians","chapter":2,"entry_index":0,"source_chapter":2,"verse":11}},{"match":"direct","source_href":"../../pulpit/colossians/2.htm","source_id":"pulpit","source_name":"Pulpit Commentary","source_ref":{"book_id":"colossians","chapter":2,"entry_index":0,"source_chapter":2,"verse":11}},{"match":"hash","source_href":"../../mhc/colossians/2.htm","source_id":"mhc","source_name":"Matthew Henry's Concise Commentary","source_ref":{"book_id":"colossians","chapter":2,"entry_index":0,"source_chapter":2,"verse":8},"text_hash":"4cdcb637c432623da6d5bc7ef3794e5228551ef5"},{"match":"direct","source_href":"../../gill/colossians/2.htm","source_id":"gill","source_name":"Gill's Exposition of the Entire Bible","source_ref":{"book_id":"colossians","chapter":2,"entry_index":0,"source_chapter":2,"verse":11}}],"12":[{"match":"direct","source_href":"../../ellicott/colossians/2.htm","source_id":"ellicott","source_name":"Ellicott's Commentary for English Readers","source_ref":{"book_id":"colossians","chapter":2,"entry_index":0,"source_chapter":2,"verse":12}},{"match":"direct","source_href":"../../pulpit/colossians/2.htm","source_id":"pulpit","source_name":"Pulpit Commentary","source_ref":{"book_id":"colossians","chapter":2,"entry_index":0,"source_chapter":2,"verse":12}},{"match":"hash","source_href":"../../mhc/colossians/2.htm","source_id":"mhc","source_name":"Matthew Henry's Concise Commentary","source_ref":{"book_id":"colossians","chapter":2,"entry_index":0,"source_chapter":2,"verse":8},"text_hash":"4cdcb637c432623da6d5bc7ef3794e5228551ef5"},{"match":"direct","source_href":"../../gill/colossians/2.htm","source_id":"gill","source_name":"Gill's Exposition of the Entire Bible","source_ref":{"book_id":"colossians","chapter":2,"entry_index":0,"source_chapter":2,"verse":12}}],"13":[{"match":"direct","source_href":"../../ellicott/colossians/2.htm","source_id":"ellicott","source_name":"Ellicott's Commentary for English Readers","source_ref":{"book_id":"colossians","chapter":2,"entry_index":0,"source_chapter":2,"verse":13}},{"match":"direct","source_href":"../../pulpit/colossians/2.htm","source_id":"pulpit","source_name":"Pulpit Commentary","source_ref":{"book_id":"colossians","chapter":2,"entry_index":0,"source_chapter":2,"verse":13}},{"match":"hash","source_href":"../../mhc/colossians/2.htm","source_id":"mhc","source_name":"Matthew Henry's Concise Commentary","source_ref":{"book_id":"colossians","chapter":2,"entry_index":0,"source_chapter":2,"verse":8},"text_hash":"4cdcb637c432623da6d5bc7ef3794e5228551ef5"},{"match":"direct","source_href":"../../gill/colossians/2.htm","source_id":"gill","source_name":"Gill's Exposition of the Entire Bible","source_ref":{"book_id":"colossians","chapter":2,"entry_index":0,"source_chapter":2,"verse":13}}],"14":[{"match":"direct","source_href":"../../ellicott/colossians/2.htm","source_id":"ellicott","source_name":"Ellicott's Commentary for English Readers","source_ref":{"book_id":"colossians","chapter":2,"entry_index":0,"source_chapter":2,"verse":14}},{"match":"direct","source_href":"../../pulpit/colossians/2.htm","source_id":"pulpit","source_name":"Pulpit Commentary","source_ref":{"book_id":"colossians","chapter":2,"entry_index":0,"source_chapter":2,"verse":14}},{"match":"hash","source_href":"../../mhc/colossians/2.htm","source_id":"mhc","source_name":"Matthew Henry's Concise Commentary","source_ref":{"book_id":"colossians","chapter":2,"entry_index":0,"source_chapter":2,"verse":8},"text_hash":"4cdcb637c432623da6d5bc7ef3794e5228551ef5"},{"match":"direct","source_href":"../../gill/colossians/2.htm","source_id":"gill","source_name":"Gill's Exposition of the Entire Bible","source_ref":{"book_id":"colossians","chapter":2,"entry_index":0,"source_chapter":2,"verse":14}}],"15":[{"match":"direct","source_href":"../../ellicott/colossians/2.htm","source_id":"ellicott","source_name":"Ellicott's Commentary for English Readers","source_ref":{"book_id":"colossians","chapter":2,"entry_index":0,"source_chapter":2,"verse":15}},{"match":"direct","source_href":"../../pulpit/colossians/2.htm","source_id":"pulpit","source_name":"Pulpit Commentary","source_ref":{"book_id":"colossians","chapter":2,"entry_index":0,"source_chapter":2,"verse":15}},{"match":"hash","source_href":"../../mhc/colossians/2.htm","source_id":"mhc","source_name":"Matthew Henry's Concise Commentary","source_ref":{"book_id":"colossians","chapter":2,"entry_index":0,"source_chapter":2,"verse":8},"text_hash":"4cdcb637c432623da6d5bc7ef3794e5228551ef5"},{"match":"direct","source_href":"../../gill/colossians/2.htm","source_id":"gill","source_name":"Gill's Exposition of the Entire Bible","source_ref":{"book_id":"colossians","chapter":2,"entry_index":0,"source_chapter":2,"verse":15}}],"16":[{"match":"direct","source_href":"../../ellicott/colossians/2.htm","source_id":"ellicott","source_name":"Ellicott's Commentary for English Readers","source_ref":{"book_id":"colossians","chapter":2,"entry_index":0,"source_chapter":2,"verse":16}},{"match":"direct","source_href":"../../pulpit/colossians/2.htm","source_id":"pulpit","source_name":"Pulpit Commentary","source_ref":{"book_id":"colossians","chapter":2,"entry_index":0,"source_chapter":2,"verse":16}},{"match":"hash","source_href":"../../mhc/colossians/2.htm","source_id":"mhc","source_name":"Matthew Henry's Concise Commentary","source_ref":{"book_id":"colossians","chapter":2,"entry_index":0,"source_chapter":2,"verse":8},"text_hash":"4cdcb637c432623da6d5bc7ef3794e5228551ef5"},{"match":"direct","source_href":"../../gill/colossians/2.htm","source_id":"gill","source_name":"Gill's Exposition of the Entire Bible","source_ref":{"book_id":"colossians","chapter":2,"entry_index":0,"source_chapter":2,"verse":16}}],"17":[{"match":"direct","source_href":"../../ellicott/colossians/2.htm","source_id":"ellicott","source_name":"Ellicott's Commentary for English Readers","source_ref":{"book_id":"colossians","chapter":2,"entry_index":0,"source_chapter":2,"verse":17}},{"match":"direct","source_href":"../../pulpit/colossians/2.htm","source_id":"pulpit","source_name":"Pulpit Commentary","source_ref":{"book_id":"colossians","chapter":2,"entry_index":0,"source_chapter":2,"verse":17}},{"match":"hash","source_href":"../../mhc/colossians/2.htm","source_id":"mhc","source_name":"Matthew Henry's Concise Commentary","source_ref":{"book_id":"colossians","chapter":2,"entry_index":0,"source_chapter":2,"verse":8},"text_hash":"4cdcb637c432623da6d5bc7ef3794e5228551ef5"},{"match":"direct","source_href":"../../gill/colossians/2.htm","source_id":"gill","source_name":"Gill's Exposition of the Entire Bible","source_ref":{"book_id":"colossians","chapter":2,"entry_index":0,"source_chapter":2,"verse":17}}],"18":[{"match":"direct","source_href":"../../ellicott/colossians/2.htm","source_id":"ellicott","source_name":"Ellicott's Commentary for English Readers","source_ref":{"book_id":"colossians","chapter":2,"entry_index":0,"source_chapter":2,"verse":18}},{"match":"direct","source_href":"../../pulpit/colossians/2.htm","source_id":"pulpit","source_name":"Pulpit Commentary","source_ref":{"book_id":"colossians","chapter":2,"entry_index":0,"source_chapter":2,"verse":18}},{"match":"direct","source_href":"../../mhc/colossians/2.htm","source_id":"mhc","source_name":"Matthew Henry's Concise Commentary","source_ref":{"book_id":"colossians","chapter":2,"entry_index":0,"source_chapter":2,"verse":18}},{"match":"direct","source_href":"../../gill/colossians/2.htm","source_id":"gill","source_name":"Gill's Exposition of the Entire Bible","source_ref":{"book_id":"colossians","chapter":2,"entry_index":0,"source_chapter":2,"verse":18}}],"19":[{"match":"direct","source_href":"../../ellicott/colossians/2.htm","source_id":"ellicott","source_name":"Ellicott's Commentary for English Readers","source_ref":{"book_id":"colossians","chapter":2,"entry_index":0,"source_chapter":2,"verse":19}},{"match":"direct","source_href":"../../pulpit/colossians/2.htm","source_id":"pulpit","source_name":"Pulpit Commentary","source_ref":{"book_id":"colossians","chapter":2,"entry_index":0,"source_chapter":2,"verse":19}},{"match":"hash","source_href":"../../mhc/colossians/2.htm","source_id":"mhc","source_name":"Matthew Henry's Concise Commentary","source_ref":{"book_id":"colossians","chapter":2,"entry_index":0,"source_chapter":2,"verse":18},"text_hash":"f18b2d898029f77ebdf9477809a71202802269dc"},{"match":"direct","source_href":"../../gill/colossians/2.htm","source_id":"gill","source_name":"Gill's Exposition of the Entire Bible","source_ref":{"book_id":"colossians","chapter":2,"entry_index":0,"source_chapter":2,"verse":19}}],"2":[{"match":"direct","source_href":"../../ellicott/colossians/2.htm","source_id":"ellicott","source_name":"Ellicott's Commentary for English Readers","source_ref":{"book_id":"colossians","chapter":2,"entry_index":0,"source_chapter":2,"verse":2}},{"match":"direct","source_href":"../../pulpit/colossians/2.htm","source_id":"pulpit","source_name":"Pulpit Commentary","source_ref":{"book_id":"colossians","chapter":2,"entry_index":0,"source_chapter":2,"verse":2}},{"match":"hash","source_href":"../../mhc/colossians/2.htm","source_id":"mhc","source_name":"Matthew Henry's Concise Commentary","source_ref":{"book_id":"colossians","chapter":2,"entry_index":0,"source_chapter":2,"verse":1},"text_hash":"d2adde7c9df5f46789364f7f48d1fc131b1184d6"},{"match":"direct","source_href":"../../gill/colossians/2.htm","source_id":"gill","source_name":"Gill's Exposition of the Entire Bible","source_ref":{"book_id":"colossians","chapter":2,"entry_index":0,"source_chapter":2,"verse":2}}],"20":[{"match":"direct","source_href":"../../ellicott/colossians/2.htm","source_id":"ellicott","source_name":"Ellicott's Commentary for English Readers","source_ref":{"book_id":"colossians","chapter":2,"entry_index":0,"source_chapter":2,"verse":20}},{"match":"direct","source_href":"../../pulpit/colossians/2.htm","source_id":"pulpit","source_name":"Pulpit Commentary","source_ref":{"book_id":"colossians","chapter":2,"entry_index":0,"source_chapter":2,"verse":20}},{"match":"hash","source_href":"../../mhc/colossians/2.htm","source_id":"mhc","source_name":"Matthew Henry's Concise Commentary","source_ref":{"book_id":"colossians","chapter":2,"entry_index":0,"source_chapter":2,"verse":18},"text_hash":"f18b2d898029f77ebdf9477809a71202802269dc"},{"match":"direct","source_href":"../../gill/colossians/2.htm","source_id":"gill","source_name":"Gill's Exposition of the Entire Bible","source_ref":{"book_id":"colossians","chapter":2,"entry_index":0,"source_chapter":2,"verse":20}}],"21":[{"match":"direct","source_href":"../../ellicott/colossians/2.htm","source_id":"ellicott","source_name":"Ellicott's Commentary for English Readers","source_ref":{"book_id":"colossians","chapter":2,"entry_index":0,"source_chapter":2,"verse":21}},{"match":"direct","source_href":"../../pulpit/colossians/2.htm","source_id":"pulpit","source_name":"Pulpit Commentary","source_ref":{"book_id":"colossians","chapter":2,"entry_index":0,"source_chapter":2,"verse":21}},{"match":"hash","source_href":"../../mhc/colossians/2.htm","source_id":"mhc","source_name":"Matthew Henry's Concise Commentary","source_ref":{"book_id":"colossians","chapter":2,"entry_index":0,"source_chapter":2,"verse":18},"text_hash":"f18b2d898029f77ebdf9477809a71202802269dc"},{"match":"direct","source_href":"../../gill/colossians/2.htm","source_id":"gill","source_name":"Gill's Exposition of the Entire Bible","source_ref":{"book_id":"colossians","chapter":2,"entry_index":0,"source_chapter":2,"verse":21}}],"22":[{"match":"direct","source_href":"../../ellicott/colossians/2.htm","source_id":"ellicott","source_name":"Ellicott's Commentary for English Readers","source_ref":{"book_id":"colossians","chapter":2,"entry_index":0,"source_chapter":2,"verse":22}},{"match":"direct","source_href":"../../pulpit/colossians/2.htm","source_id":"pulpit","source_name":"Pulpit Commentary","source_ref":{"book_id":"colossians","chapter":2,"entry_index":0,"source_chapter":2,"verse":22}},{"match":"hash","source_href":"../../mhc/colossians/2.htm","source_id":"mhc","source_name":"Matthew Henry's Concise Commentary","source_ref":{"book_id":"colossians","chapter":2,"entry_index":0,"source_chapter":2,"verse":18},"text_hash":"f18b2d898029f77ebdf9477809a71202802269dc"},{"match":"direct","source_href":"../../gill/colossians/2.htm","source_id":"gill","source_name":"Gill's Exposition of the Entire Bible","source_ref":{"book_id":"colossians","chapter":2,"entry_index":0,"source_chapter":2,"verse":22}}],"23":[{"match":"direct","source_href":"../../ellicott/colossians/2.htm","source_id":"ellicott","source_name":"Ellicott's Commentary for English Readers","source_ref":{"book_id":"colossians","chapter":2,"entry_index":0,"source_chapter":2,"verse":23}},{"match":"direct","source_href":"../../pulpit/colossians/2.htm","source_id":"pulpit","source_name":"Pulpit Commentary","source_ref":{"book_id":"colossians","chapter":2,"entry_index":0,"source_chapter":2,"verse":23}},{"match":"hash","source_href":"../../mhc/colossians/2.htm","source_id":"mhc","source_name":"Matthew Henry's Concise Commentary","source_ref":{"book_id":"colossians","chapter":2,"entry_index":0,"source_chapter":2,"verse":18},"text_hash":"f18b2d898029f77ebdf9477809a71202802269dc"},{"match":"direct","source_href":"../../gill/colossians/2.htm","source_id":"gill","source_name":"Gill's Exposition of the Entire Bible","source_ref":{"book_id":"colossians","chapter":2,"entry_index":0,"source_chapter":3,"verse":23}}],"3":[{"match":"direct","source_href":"../../ellicott/colossians/2.htm","source_id":"ellicott","source_name":"Ellicott's Commentary for English Readers","source_ref":{"book_id":"colossians","chapter":2,"entry_index":0,"source_chapter":2,"verse":3}},{"match":"direct","source_href":"../../pulpit/colossians/2.htm","source_id":"pulpit","source_name":"Pulpit Commentary","source_ref":{"book_id":"colossians","chapter":2,"entry_index":0,"source_chapter":2,"verse":3}},{"match":"hash","source_href":"../../mhc/colossians/2.htm","source_id":"mhc","source_name":"Matthew Henry's Concise Commentary","source_ref":{"book_id":"colossians","chapter":2,"entry_index":0,"source_chapter":2,"verse":1},"text_hash":"d2adde7c9df5f46789364f7f48d1fc131b1184d6"},{"match":"direct","source_href":"../../gill/colossians/2.htm","source_id":"gill","source_name":"Gill's Exposition of the Entire Bible","source_ref":{"book_id":"colossians","chapter":2,"entry_index":0,"source_chapter":2,"verse":3}}],"4":[{"match":"direct","source_href":"../../ellicott/colossians/2.htm","source_id":"ellicott","source_name":"Ellicott's Commentary for English Readers","source_ref":{"book_id":"colossians","chapter":2,"entry_index":0,"source_chapter":2,"verse":4}},{"match":"direct","source_href":"../../pulpit/colossians/2.htm","source_id":"pulpit","source_name":"Pulpit Commentary","source_ref":{"book_id":"colossians","chapter":2,"entry_index":0,"source_chapter":2,"verse":4}},{"match":"hash","source_href":"../../mhc/colossians/2.htm","source_id":"mhc","source_name":"Matthew Henry's Concise Commentary","source_ref":{"book_id":"colossians","chapter":2,"entry_index":0,"source_chapter":2,"verse":1},"text_hash":"d2adde7c9df5f46789364f7f48d1fc131b1184d6"},{"match":"direct","source_href":"../../gill/colossians/2.htm","source_id":"gill","source_name":"Gill's Exposition of the Entire Bible","source_ref":{"book_id":"colossians","chapter":2,"entry_index":0,"source_chapter":2,"verse":4}}],"5":[{"match":"direct","source_href":"../../ellicott/colossians/2.htm","source_id":"ellicott","source_name":"Ellicott's Commentary for English Readers","source_ref":{"book_id":"colossians","chapter":2,"entry_index":0,"source_chapter":2,"verse":5}},{"match":"direct","source_href":"../../pulpit/colossians/2.htm","source_id":"pulpit","source_name":"Pulpit Commentary","source_ref":{"book_id":"colossians","chapter":2,"entry_index":0,"source_chapter":2,"verse":5}},{"match":"hash","source_href":"../../mhc/colossians/2.htm","source_id":"mhc","source_name":"Matthew Henry's Concise Commentary","source_ref":{"book_id":"colossians","chapter":2,"entry_index":0,"source_chapter":2,"verse":1},"text_hash":"d2adde7c9df5f46789364f7f48d1fc131b1184d6"},{"match":"direct","source_href":"../../gill/colossians/2.htm","source_id":"gill","source_name":"Gill's Exposition of the Entire Bible","source_ref":{"book_id":"colossians","chapter":2,"entry_index":0,"source_chapter":2,"verse":5}}],"6":[{"match":"direct","source_href":"../../ellicott/colossians/2.htm","source_id":"ellicott","source_name":"Ellicott's Commentary for English Readers","source_ref":{"book_id":"colossians","chapter":2,"entry_index":0,"source_chapter":2,"verse":6}},{"match":"direct","source_href":"../../pulpit/colossians/2.htm","source_id":"pulpit","source_name":"Pulpit Commentary","source_ref":{"book_id":"colossians","chapter":2,"entry_index":0,"source_chapter":2,"verse":6}},{"match":"hash","source_href":"../../mhc/colossians/2.htm","source_id":"mhc","source_name":"Matthew Henry's Concise Commentary","source_ref":{"book_id":"colossians","chapter":2,"entry_index":0,"source_chapter":2,"verse":1},"text_hash":"d2adde7c9df5f46789364f7f48d1fc131b1184d6"},{"match":"direct","source_href":"../../gill/colossians/2.htm","source_id":"gill","source_name":"Gill's Exposition of the Entire Bible","source_ref":{"book_id":"colossians","chapter":2,"entry_index":0,"source_chapter":2,"verse":6}}],"7":[{"match":"direct","source_href":"../../ellicott/colossians/2.htm","source_id":"ellicott","source_name":"Ellicott's Commentary for English Readers","source_ref":{"book_id":"colossians","chapter":2,"entry_index":0,"source_chapter":2,"verse":7}},{"match":"direct","source_href":"../../pulpit/colossians/2.htm","source_id":"pulpit","source_name":"Pulpit Commentary","source_ref":{"book_id":"colossians","chapter":2,"entry_index":0,"source_chapter":2,"verse":7}},{"match":"hash","source_href":"../../mhc/colossians/2.htm","source_id":"mhc","source_name":"Matthew Henry's Concise Commentary","source_ref":{"book_id":"colossians","chapter":2,"entry_index":0,"source_chapter":2,"verse":1},"text_hash":"d2adde7c9df5f46789364f7f48d1fc131b1184d6"},{"match":"direct","source_href":"../../gill/colossians/2.htm","source_id":"gill","source_name":"Gill's Exposition of the Entire Bible","source_ref":{"book_id":"colossians","chapter":2,"entry_index":0,"source_chapter":2,"verse":7}}],"8":[{"match":"direct","source_href":"../../ellicott/colossians/2.htm","source_id":"ellicott","source_name":"Ellicott's Commentary for English Readers","source_ref":{"book_id":"colossians","chapter":2,"entry_index":0,"source_chapter":2,"verse":8}},{"match":"direct","source_href":"../../pulpit/colossians/2.htm","source_id":"pulpit","source_name":"Pulpit Commentary","source_ref":{"book_id":"colossians","chapter":2,"entry_index":0,"source_chapter":2,"verse":8}},{"match":"direct","source_href":"../../mhc/colossians/2.htm","source_id":"mhc","source_name":"Matthew Henry's Concise Commentary","source_ref":{"book_id":"colossians","chapter":2,"entry_index":0,"source_chapter":2,"verse":8}},{"match":"direct","source_href":"../../gill/colossians/2.htm","source_id":"gill","source_name":"Gill's Exposition of the Entire Bible","source_ref":{"book_id":"colossians","chapter":2,"entry_index":0,"source_chapter":2,"verse":8}}],"9":[{"match":"direct","source_href":"../../ellicott/colossians/2.htm","source_id":"ellicott","source_name":"Ellicott's Commentary for English Readers","source_ref":{"book_id":"colossians","chapter":2,"entry_index":0,"source_chapter":2,"verse":9}},{"match":"direct","source_href":"../../pulpit/colossians/2.htm","source_id":"pulpit","source_name":"Pulpit Commentary","source_ref":{"book_id":"colossians","chapter":2,"entry_index":0,"source_chapter":2,"verse":9}},{"match":"hash","source_href":"../../mhc/colossians/2.htm","source_id":"mhc","source_name":"Matthew Henry's Concise Commentary","source_ref":{"book_id":"colossians","chapter":2,"entry_index":0,"source_chapter":2,"verse":8},"text_hash":"4cdcb637c432623da6d5bc7ef3794e5228551ef5"},{"match":"direct","source_href":"../../gill/colossians/2.htm","source_id":"gill","source_name":"Gill's Exposition of the Entire Bible","source_ref":{"book_id":"colossians","chapter":2,"entry_index":0,"source_chapter":2,"verse":9}}]},"3":{"1":[{"match":"direct","source_href":"../../ellicott/colossians/3.htm","source_id":"ellicott","source_name":"Ellicott's Commentary for English Readers","source_ref":{"book_id":"colossians","chapter":3,"entry_index":0,"source_chapter":3,"verse":1}},{"match":"direct","source_href":"../../pulpit/colossians/3.htm","source_id":"pulpit","source_name":"Pulpit Commentary","source_ref":{"book_id":"colossians","chapter":3,"entry_index":0,"source_chapter":3,"verse":1}},{"match":"direct","source_href":"../../mhc/colossians/3.htm","source_id":"mhc","source_name":"Matthew Henry's Concise Commentary","source_ref":{"book_id":"colossians","chapter":3,"entry_index":0,"source_chapter":3,"verse":1}},{"match":"direct","source_href":"../../gill/colossians/3.htm","source_id":"gill","source_name":"Gill's Exposition of the Entire Bible","source_ref":{"book_id":"colossians","chapter":3,"entry_index":0,"source_chapter":3,"verse":1}}],"10":[{"match":"direct","source_href":"../../ellicott/colossians/3.htm","source_id":"ellicott","source_name":"Ellicott's Commentary for English Readers","source_ref":{"book_id":"colossians","chapter":3,"entry_index":0,"source_chapter":3,"verse":10}},{"match":"direct","source_href":"../../pulpit/colossians/3.htm","source_id":"pulpit","source_name":"Pulpit Commentary","source_ref":{"book_id":"colossians","chapter":3,"entry_index":0,"source_chapter":3,"verse":10}},{"match":"hash","source_href":"../../mhc/colossians/3.htm","source_id":"mhc","source_name":"Matthew Henry's Concise Commentary","source_ref":{"book_id":"colossians","chapter":3,"entry_index":0,"source_chapter":3,"verse":5},"text_hash":"0a3e9d67d17c31d1abdfc594df2d85f61e5522d4"},{"match":"direct","source_href":"../../gill/colossians/3.htm","source_id":"gill","source_name":"Gill's Exposition of the Entire Bible","source_ref":{"book_id":"colossians","chapter":3,"entry_index":0,"source_chapter":3,"verse":10}}],"11":[{"match":"direct","source_href":"../../ellicott/colossians/3.htm","source_id":"ellicott","source_name":"Ellicott's Commentary for English Readers","source_ref":{"book_id":"colossians","chapter":3,"entry_index":0,"source_chapter":3,"verse":11}},{"match":"direct","source_href":"../../pulpit/colossians/3.htm","source_id":"pulpit","source_name":"Pulpit Commentary","source_ref":{"book_id":"colossians","chapter":3,"entry_index":0,"source_chapter":3,"verse":11}},{"match":"hash","source_href":"../../mhc/colossians/3.htm","source_id":"mhc","source_name":"Matthew Henry's Concise Commentary","source_ref":{"book_id":"colossians","chapter":3,"entry_index":0,"source_chapter":3,"verse":5},"text_hash":"0a3e9d67d17c31d1abdfc594df2d85f61e5522d4"},{"match":"direct","source_href":"../../gill/colossians/3.htm","source_id":"gill","source_name":"Gill's Exposition of the Entire Bible","source_ref":{"book_id":"colossians","chapter":3,"entry_index":0,"source_chapter":3,"verse":11}}],"12":[{"match":"direct","source_href":"../../ellicott/colossians/3.htm","source_id":"ellicott","source_name":"Ellicott's Commentary for English Readers","source_ref":{"book_id":"colossians","chapter":3,"entry_index":0,"source_chapter":3,"verse":12}},{"match":"direct","source_href":"../../pulpit/colossians/3.htm","source_id":"pulpit","source_name":"Pulpit Commentary","source_ref":{"book_id":"colossians","chapter":3,"entry_index":0,"source_chapter":3,"verse":12}},{"match":"direct","source_href":"../../mhc/colossians/3.htm","source_id":"mhc","source_name":"Matthew Henry's Concise Commentary","source_ref":{"book_id":"colossians","chapter":3,"entry_index":0,"source_chapter":3,"verse":12}},{"match":"direct","source_href":"../../gill/colossians/3.htm","source_id":"gill","source_name":"Gill's Exposition of the Entire Bible","source_ref":{"book_id":"colossians","chapter":3,"entry_index":0,"source_chapter":3,"verse":12}}],"13":[{"match":"direct","source_href":"../../ellicott/colossians/3.htm","source_id":"ellicott","source_name":"Ellicott's Commentary for English Readers","source_ref":{"book_id":"colossians","chapter":3,"entry_index":0,"source_chapter":3,"verse":13}},{"match":"direct","source_href":"../../pulpit/colossians/3.htm","source_id":"pulpit","source_name":"Pulpit Commentary","source_ref":{"book_id":"colossians","chapter":3,"entry_index":0,"source_chapter":3,"verse":13}},{"match":"hash","source_href":"../../mhc/colossians/3.htm","source_id":"mhc","source_name":"Matthew Henry's Concise Commentary","source_ref":{"book_id":"colossians","chapter":3,"entry_index":0,"source_chapter":3,"verse":12},"text_hash":"661ec98755f3b273265c85c98c8b30631469a4af"},{"match":"direct","source_href":"../../gill/colossians/3.htm","source_id":"gill","source_name":"Gill's Exposition of the Entire Bible","source_ref":{"book_id":"colossians","chapter":3,"entry_index":0,"source_chapter":3,"verse":13}}],"14":[{"match":"direct","source_href":"../../ellicott/colossians/3.htm","source_id":"ellicott","source_name":"Ellicott's Commentary for English Readers","source_ref":{"book_id":"colossians","chapter":3,"entry_index":0,"source_chapter":3,"verse":14}},{"match":"direct","source_href":"../../pulpit/colossians/3.htm","source_id":"pulpit","source_name":"Pulpit Commentary","source_ref":{"book_id":"colossians","chapter":3,"entry_index":0,"source_chapter":3,"verse":14}},{"match":"hash","source_href":"../../mhc/colossians/3.htm","source_id":"mhc","source_name":"Matthew Henry's Concise Commentary","source_ref":{"book_id":"colossians","chapter":3,"entry_index":0,"source_chapter":3,"verse":12},"text_hash":"661ec98755f3b273265c85c98c8b30631469a4af"},{"match":"direct","source_href":"../../gill/colossians/3.htm","source_id":"gill","source_name":"Gill's Exposition of the Entire Bible","source_ref":{"book_id":"colossians","chapter":3,"entry_index":0,"source_chapter":3,"verse":14}}],"15":[{"match":"direct","source_href":"../../ellicott/colossians/3.htm","source_id":"ellicott","source_name":"Ellicott's Commentary for English Readers","source_ref":{"book_id":"colossians","chapter":3,"entry_index":0,"source_chapter":3,"verse":15}},{"match":"direct","source_href":"../../pulpit/colossians/3.htm","source_id":"pulpit","source_name":"Pulpit Commentary","source_ref":{"book_id":"colossians","chapter":3,"entry_index":0,"source_chapter":3,"verse":15}},{"match":"hash","source_href":"../../mhc/colossians/3.htm","source_id":"mhc","source_name":"Matthew Henry's Concise Commentary","source_ref":{"book_id":"colossians","chapter":3,"entry_index":0,"source_chapter":3,"verse":12},"text_hash":"661ec98755f3b273265c85c98c8b30631469a4af"},{"match":"direct","source_href":"../../gill/colossians/3.htm","source_id":"gill","source_name":"Gill's Exposition of the Entire Bible","source_ref":{"book_id":"colossians","chapter":3,"entry_index":0,"source_chapter":3,"verse":15}}],"16":[{"match":"direct","source_href":"../../ellicott/colossians/3.htm","source_id":"ellicott","source_name":"Ellicott's Commentary for English Readers","source_ref":{"book_id":"colossians","chapter":3,"entry_index":0,"source_chapter":3,"verse":16}},{"match":"direct","source_href":"../../pulpit/colossians/3.htm","source_id":"pulpit","source_name":"Pulpit Commentary","source_ref":{"book_id":"colossians","chapter":3,"entry_index":0,"source_chapter":3,"verse":16}},{"match":"hash","source_href":"../../mhc/colossians/3.htm","source_id":"mhc","source_name":"Matthew Henry's Concise Commentary","source_ref":{"book_id":"colossians","chapter":3,"entry_index":0,"source_chapter":3,"verse":12},"text_hash":"661ec98755f3b273265c85c98c8b30631469a4af"},{"match":"direct","source_href":"../../gill/colossians/3.htm","source_id":"gill","source_name":"Gill's Exposition of the Entire Bible","source_ref":{"book_id":"colossians","chapter":3,"entry_index":0,"source_chapter":3,"verse":16}}],"17":[{"match":"direct","source_href":"../../ellicott/colossians/3.htm","source_id":"ellicott","source_name":"Ellicott's Commentary for English Readers","source_ref":{"book_id":"colossians","chapter":3,"entry_index":0,"source_chapter":3,"verse":17}},{"match":"direct","source_href":"../../pulpit/colossians/3.htm","source_id":"pulpit","source_name":"Pulpit Commentary","source_ref":{"book_id":"colossians","chapter":3,"entry_index":0,"source_chapter":3,"verse":17}},{"match":"hash","source_href":"../../mhc/colossians/3.htm","source_id":"mhc","source_name":"Matthew Henry's Concise Commentary","source_ref":{"book_id":"colossians","chapter":3,"entry_index":0,"source_chapter":3,"verse":12},"text_hash":"661ec98755f3b273265c85c98c8b30631469a4af"},{"match":"direct","source_href":"../../gill/colossians/3.htm","source_id":"gill","source_name":"Gill's Exposition of the Entire Bible","source_ref":{"book_id":"colossians","chapter":3,"entry_index":0,"source_chapter":3,"verse":17}}],"18":[{"match":"direct","source_href":"../../ellicott/colossians/3.htm","source_id":"ellicott","source_name":"Ellicott's Commentary for English Readers","source_ref":{"book_id":"colossians","chapter":3,"entry_index":0,"source_chapter":3,"verse":18}},{"match":"direct","source_href":"../../pulpit/colossians/3.htm","source_id":"pulpit","source_name":"Pulpit Commentary","source_ref":{"book_id":"colossians","chapter":3,"entry_index":0,"source_chapter":3,"verse":18}},{"match":"direct","source_href":"../../mhc/colossians/3.htm","source_id":"mhc","source_name":"Matthew Henry's Concise Commentary","source_ref":{"book_id":"colossians","chapter":3,"entry_index":0,"source_chapter":3,"verse":18}},{"match":"direct","source_href":"../../gill/colossians/3.htm","source_id":"gill","source_name":"Gill's Exposition of the Entire Bible","source_ref":{"book_id":"colossians","chapter":3,"entry_index":0,"source_chapter":3,"verse":18}}],"19":[{"match":"direct","source_href":"../../ellicott/colossians/3.htm","source_id":"ellicott","source_name":"Ellicott's Commentary for English Readers","source_ref":{"book_id":"colossians","chapter":3,"entry_index":0,"source_chapter":3,"verse":19}},{"match":"direct","source_href":"../../pulpit/colossians/3.htm","source_id":"pulpit","source_name":"Pulpit Commentary","source_ref":{"book_id":"colossians","chapter":3,"entry_index":0,"source_chapter":3,"verse":19}},{"match":"hash","source_href":"../../mhc/colossians/3.htm","source_id":"mhc","source_name":"Matthew Henry's Concise Commentary","source_ref":{"book_id":"colossians","chapter":3,"entry_index":0,"source_chapter":3,"verse":18},"text_hash":"c372f7937316d0721ba04343dbe054c1aec1fe2d"},{"match":"direct","source_href":"../../gill/colossians/3.htm","source_id":"gill","source_name":"Gill's Exposition of the Entire Bible","source_ref":{"book_id":"colossians","chapter":3,"entry_index":0,"source_chapter":3,"verse":19}}],"2":[{"match":"hash","source_href":"../../mhc/colossians/3.htm","source_id":"mhc","source_name":"Matthew Henry's Concise Commentary","source_ref":{"book_id":"colossians","chapter":3,"entry_index":0,"source_chapter":3,"verse":1},"text_hash":"1bcde5d882750f9be696ab9cdf6d738dd7108272"},{"match":"direct","source_href":"../../gill/colossians/3.htm","source_id":"gill","source_name":"Gill's Exposition of the Entire Bible","source_ref":{"book_id":"colossians","chapter":3,"entry_index":0,"source_chapter":3,"verse":2}}],"20":[{"match":"direct","source_href":"../../pulpit/colossians/3.htm","source_id":"pulpit","source_name":"Pulpit Commentary","source_ref":{"book_id":"colossians","chapter":3,"entry_index":0,"source_chapter":3,"verse":20}},{"match":"hash","source_href":"../../mhc/colossians/3.htm","source_id":"mhc","source_name":"Matthew Henry's Concise Commentary","source_ref":{"book_id":"colossians","chapter":3,"entry_index":0,"source_chapter":3,"verse":18},"text_hash":"c372f7937316d0721ba04343dbe054c1aec1fe2d"},{"match":"direct","source_href":"../../gill/colossians/3.htm","source_id":"gill","source_name":"Gill's Exposition of the Entire Bible","source_ref":{"book_id":"colossians","chapter":3,"entry_index":0,"source_chapter":3,"verse":20}}],"21":[{"match":"direct","source_href":"../../ellicott/colossians/3.htm","source_id":"ellicott","source_name":"Ellicott's Commentary for English Readers","source_ref":{"book_id":"colossians","chapter":3,"entry_index":0,"source_chapter":3,"verse":21}},{"match":"direct","source_href":"../../pulpit/colossians/3.htm","source_id":"pulpit","source_name":"Pulpit Commentary","source_ref":{"book_id":"colossians","chapter":3,"entry_index":0,"source_chapter":3,"verse":21}},{"match":"hash","source_href":"../../mhc/colossians/3.htm","source_id":"mhc","source_name":"Matthew Henry's Concise Commentary","source_ref":{"book_id":"colossians","chapter":3,"entry_index":0,"source_chapter":3,"verse":18},"text_hash":"c372f7937316d0721ba04343dbe054c1aec1fe2d"},{"match":"direct","source_href":"../../gill/colossians/3.htm","source_id":"gill","source_name":"Gill's Exposition of the Entire Bible","source_ref":{"book_id":"colossians","chapter":3,"entry_index":0,"source_chapter":3,"verse":21}}],"22":[{"match":"direct","source_href":"../../ellicott/colossians/3.htm","source_id":"ellicott","source_name":"Ellicott's Commentary for English Readers","source_ref":{"book_id":"colossians","chapter":3,"entry_index":0,"source_chapter":3,"verse":22}},{"match":"direct","source_href":"../../pulpit/colossians/3.htm","source_id":"pulpit","source_name":"Pulpit Commentary","source_ref":{"book_id":"colossians","chapter":3,"entry_index":0,"source_chapter":3,"verse":22}},{"match":"hash","source_href":"../../mhc/colossians/3.htm","source_id":"mhc","source_name":"Matthew Henry's Concise Commentary","source_ref":{"book_id":"colossians","chapter":3,"entry_index":0,"source_chapter":3,"verse":18},"text_hash":"c372f7937316d0721ba04343dbe054c1aec1fe2d"},{"match":"direct","source_href":"../../gill/colossians/3.htm","source_id":"gill","source_name":"Gill's Exposition of the Entire Bible","source_ref":{"book_id":"colossians","chapter":3,"entry_index":0,"source_chapter":3,"verse":22}}],"23":[{"match":"direct","source_href":"../../pulpit/colossians/3.htm","source_id":"pulpit","source_name":"Pulpit Commentary","source_ref":{"book_id":"colossians","chapter":3,"entry_index":0,"source_chapter":3,"verse":23}},{"match":"hash","source_href":"../../mhc/colossians/3.htm","source_id":"mhc","source_name":"Matthew Henry's Concise Commentary","source_ref":{"book_id":"colossians","chapter":3,"entry_index":0,"source_chapter":3,"verse":18},"text_hash":"c372f7937316d0721ba04343dbe054c1aec1fe2d"},{"match":"direct","source_href":"../../gill/colossians/3.htm","source_id":"gill","source_name":"Gill's Exposition of the Entire Bible","source_ref":{"book_id":"colossians","chapter":3,"entry_index":0,"source_chapter":3,"verse":23}}],"24":[{"match":"direct","source_href":"../../pulpit/colossians/3.htm","source_id":"pulpit","source_name":"Pulpit Commentary","source_ref":{"book_id":"colossians","chapter":3,"entry_index":0,"source_chapter":3,"verse":24}},{"match":"hash","source_href":"../../mhc/colossians/3.htm","source_id":"mhc","source_name":"Matthew Henry's Concise Commentary","source_ref":{"book_id":"colossians","chapter":3,"entry_index":0,"source_chapter":3,"verse":18},"text_hash":"c372f7937316d0721ba04343dbe054c1aec1fe2d"},{"match":"direct","source_href":"../../gill/colossians/3.htm","source_id":"gill","source_name":"Gill's Exposition of the Entire Bible","source_ref":{"book_id":"colossians","chapter":3,"entry_index":0,"source_chapter":3,"verse":24}}],"25":[{"match":"direct","source_href":"../../ellicott/colossians/3.htm","source_id":"ellicott","source_name":"Ellicott's Commentary for English Readers","source_ref":{"book_id":"colossians","chapter":3,"entry_index":0,"source_chapter":3,"verse":25}},{"match":"direct","source_href":"../../pulpit/colossians/3.htm","source_id":"pulpit","source_name":"Pulpit Commentary","source_ref":{"book_id":"colossians","chapter":3,"entry_index":0,"source_chapter":3,"verse":25}},{"match":"hash","source_href":"../../mhc/colossians/3.htm","source_id":"mhc","source_name":"Matthew Henry's Concise Commentary","source_ref":{"book_id":"colossians","chapter":3,"entry_index":0,"source_chapter":3,"verse":18},"text_hash":"c372f7937316d0721ba04343dbe054c1aec1fe2d"},{"match":"direct","source_href":"../../gill/colossians/3.htm","source_id":"gill","source_name":"Gill's Exposition of the Entire Bible","source_ref":{"book_id":"colossians","chapter":3,"entry_index":0,"source_chapter":4,"verse":25}}],"3":[{"match":"direct","source_href":"../../ellicott/colossians/3.htm","source_id":"ellicott","source_name":"Ellicott's Commentary for English Readers","source_ref":{"book_id":"colossians","chapter":3,"entry_index":0,"source_chapter":3,"verse":3}},{"match":"direct","source_href":"../../pulpit/colossians/3.htm","source_id":"pulpit","source_name":"Pulpit Commentary","source_ref":{"book_id":"colossians","chapter":3,"entry_index":0,"source_chapter":3,"verse":3}},{"match":"hash","source_href":"../../mhc/colossians/3.htm","source_id":"mhc","source_name":"Matthew Henry's Concise Commentary","source_ref":{"book_id":"colossians","chapter":3,"entry_index":0,"source_chapter":3,"verse":1},"text_hash":"1bcde5d882750f9be696ab9cdf6d738dd7108272"},{"match":"direct","source_href":"../../gill/colossians/3.htm","source_id":"gill","source_name":"Gill's Exposition of the Entire Bible","source_ref":{"book_id":"colossians","chapter":3,"entry_index":0,"source_chapter":3,"verse":3}}],"4":[{"match":"direct","source_href":"../../ellicott/colossians/3.htm","source_id":"ellicott","source_name":"Ellicott's Commentary for English Readers","source_ref":{"book_id":"colossians","chapter":3,"entry_index":0,"source_chapter":3,"verse":4}},{"match":"direct","source_href":"../../pulpit/colossians/3.htm","source_id":"pulpit","source_name":"Pulpit Commentary","source_ref":{"book_id":"colossians","chapter":3,"entry_index":0,"source_chapter":3,"verse":4}},{"match":"hash","source_href":"../../mhc/colossians/3.htm","source_id":"mhc","source_name":"Matthew Henry's Concise Commentary","source_ref":{"book_id":"colossians","chapter":3,"entry_index":0,"source_chapter":3,"verse":1},"text_hash":"1bcde5d882750f9be696ab9cdf6d738dd7108272"},{"match":"direct","source_href":"../../gill/colossians/3.htm","source_id":"gill","source_name":"Gill's Exposition of the Entire Bible","source_ref":{"book_id":"colossians","chapter":3,"entry_index":0,"source_chapter":3,"verse":4}}],"5":[{"match":"direct","source_href":"../../ellicott/colossians/3.htm","source_id":"ellicott","source_name":"Ellicott's Commentary for English Readers","source_ref":{"book_id":"colossians","chapter":3,"entry_index":0,"source_chapter":3,"verse":5}},{"match":"direct","source_href":"../../pulpit/colossians/3.htm","source_id":"pulpit","source_name":"Pulpit Commentary","source_ref":{"book_id":"colossians","chapter":3,"entry_index":0,"source_chapter":3,"verse":5}},{"match":"direct","source_href":"../../mhc/colossians/3.htm","source_id":"mhc","source_name":"Matthew Henry's Concise Commentary","source_ref":{"book_id":"colossians","chapter":3,"entry_index":0,"source_chapter":3,"verse":5}},{"match":"direct","source_href":"../../gill/colossians/3.htm","source_id":"gill","source_name":"Gill's Exposition of the Entire Bible","source_ref":{"book_id":"colossians","chapter":3,"entry_index":0,"source_chapter":3,"verse":5}}],"6":[{"match":"direct","source_href":"../../pulpit/colossians/3.htm","source_id":"pulpit","source_name":"Pulpit Commentary","source_ref":{"book_id":"colossians","chapter":3,"entry_index":0,"source_chapter":3,"verse":6}},{"match":"hash","source_href":"../../mhc/colossians/3.htm","source_id":"mhc","source_name":"Matthew Henry's Concise Commentary","source_ref":{"book_id":"colossians","chapter":3,"entry_index":0,"source_chapter":3,"verse":5},"text_hash":"0a3e9d67d17c31d1abdfc594df2d85f61e5522d4"},{"match":"direct","source_href":"../../gill/colossians/3.htm","source_id":"gill","source_name":"Gill's Exposition of the Entire Bible","source_ref":{"book_id":"colossians","chapter":3,"entry_index":0,"source_chapter":3,"verse":6}}],"7":[{"match":"direct","source_href":"../../ellicott/colossians/3.htm","source_id":"ellicott","source_name":"Ellicott's Commentary for English Readers","source_ref":{"book_id":"colossians","chapter":3,"entry_index":0,"source_chapter":3,"verse":7}},{"match":"direct","source_href":"../../pulpit/colossians/3.htm","source_id":"pulpit","source_name":"Pulpit Commentary","source_ref":{"book_id":"colossians","chapter":3,"entry_index":0,"source_chapter":3,"verse":7}},{"match":"hash","source_href":"../../mhc/colossians/3.htm","source_id":"mhc","source_name":"Matthew Henry's Concise Commentary","source_ref":{"book_id":"colossians","chapter":3,"entry_index":0,"source_chapter":3,"verse":5},"text_hash":"0a3e9d67d17c31d1abdfc594df2d85f61e5522d4"},{"match":"direct","source_href":"../../gill/colossians/3.htm","source_id":"gill","source_name":"Gill's Exposition of the Entire Bible","source_ref":{"book_id":"colossians","chapter":3,"entry_index":0,"source_chapter":3,"verse":7}}],"8":[{"match":"direct","source_href":"../../ellicott/colossians/3.htm","source_id":"ellicott","source_name":"Ellicott's Commentary for English Readers","source_ref":{"book_id":"colossians","chapter":3,"entry_index":0,"source_chapter":3,"verse":8}},{"match":"direct","source_href":"../../pulpit/colossians/3.htm","source_id":"pulpit","source_name":"Pulpit Commentary","source_ref":{"book_id":"colossians","chapter":3,"entry_index":0,"source_chapter":3,"verse":8}},{"match":"hash","source_href":"../../mhc/colossians/3.htm","source_id":"mhc","source_name":"Matthew Henry's Concise Commentary","source_ref":{"book_id":"colossians","chapter":3,"entry_index":0,"source_chapter":3,"verse":5},"text_hash":"0a3e9d67d17c31d1abdfc594df2d85f61e5522d4"},{"match":"direct","source_href":"../../gill/colossians/3.htm","source_id":"gill","source_name":"Gill's Exposition of the Entire Bible","source_ref":{"book_id":"colossians","chapter":3,"entry_index":0,"source_chapter":3,"verse":8}}],"9":[{"match":"direct","source_href":"../../ellicott/colossians/3.htm","source_id":"ellicott","source_name":"Ellicott's Commentary for English Readers","source_ref":{"book_id":"colossians","chapter":3,"entry_index":0,"source_chapter":3,"verse":9}},{"match":"direct","source_href":"../../pulpit/colossians/3.htm","source_id":"pulpit","source_name":"Pulpit Commentary","source_ref":{"book_id":"colossians","chapter":3,"entry_index":0,"source_chapter":3,"verse":9}},{"match":"hash","source_href":"../../mhc/colossians/3.htm","source_id":"mhc","source_name":"Matthew Henry's Concise Commentary","source_ref":{"book_id":"colossians","chapter":3,"entry_index":0,"source_chapter":3,"verse":5},"text_hash":"0a3e9d67d17c31d1abdfc594df2d85f61e5522d4"},{"match":"direct","source_href":"../../gill/colossians/3.htm","source_id":"gill","source_name":"Gill's Exposition of the Entire Bible","source_ref":{"book_id":"colossians","chapter":3,"entry_index":0,"source_chapter":3,"verse":9}}]},"4":{"1":[{"match":"direct","source_href":"../../ellicott/colossians/4.htm","source_id":"ellicott","source_name":"Ellicott's Commentary for English Readers","source_ref":{"book_id":"colossians","chapter":4,"entry_index":0,"source_chapter":4,"verse":1}},{"match":"direct","source_href":"../../pulpit/colossians/4.htm","source_id":"pulpit","source_name":"Pulpit Commentary","source_ref":{"book_id":"colossians","chapter":4,"entry_index":0,"source_chapter":4,"verse":1}},{"match":"direct","source_href":"../../mhc/colossians/4.htm","source_id":"mhc","source_name":"Matthew Henry's Concise Commentary","source_ref":{"book_id":"colossians","chapter":4,"entry_index":0,"source_chapter":4,"verse":1}},{"match":"direct","source_href":"../../gill/colossians/4.htm","source_id":"gill","source_name":"Gill's Exposition of the Entire Bible","source_ref":{"book_id":"colossians","chapter":4,"entry_index":0,"source_chapter":4,"verse":1}}],"10":[{"match":"direct","source_href":"../../ellicott/colossians/4.htm","source_id":"ellicott","source_name":"Ellicott's Commentary for English Readers","source_ref":{"book_id":"colossians","chapter":4,"entry_index":0,"source_chapter":4,"verse":10}},{"match":"direct","source_href":"../../pulpit/colossians/4.htm","source_id":"pulpit","source_name":"Pulpit Commentary","source_ref":{"book_id":"colossians","chapter":4,"entry_index":0,"source_chapter":4,"verse":10}},{"match":"direct","source_href":"../../mhc/colossians/4.htm","source_id":"mhc","source_name":"Matthew Henry's Concise Commentary","source_ref":{"book_id":"colossians","chapter":4,"entry_index":0,"source_chapter":4,"verse":10}},{"match":"direct","source_href":"../../gill/colossians/4.htm","source_id":"gill","source_name":"Gill's Exposition of the Entire Bible","source_ref":{"book_id":"colossians","chapter":4,"entry_index":0,"source_chapter":4,"verse":10}}],"11":[{"match":"direct","source_href":"../../ellicott/colossians/4.htm","source_id":"ellicott","source_name":"Ellicott's Commentary for English Readers","source_ref":{"book_id":"colossians","chapter":4,"entry_index":0,"source_chapter":4,"verse":11}},{"match":"direct","source_href":"../../pulpit/colossians/4.htm","source_id":"pulpit","source_name":"Pulpit Commentary","source_ref":{"book_id":"colossians","chapter":4,"entry_index":0,"source_chapter":4,"verse":11}},{"match":"hash","source_href":"../../mhc/colossians/4.htm","source_id":"mhc","source_name":"Matthew Henry's Concise Commentary","source_ref":{"book_id":"colossians","chapter":4,"entry_index":0,"source_chapter":4,"verse":10},"text_hash":"043e21e3c6a088c85d12faa6cdc25ef67d3515fc"},{"match":"direct","source_href":"../../gill/colossians/4.htm","source_id":"gill","source_name":"Gill's Exposition of the Entire Bible","source_ref":{"book_id":"colossians","chapter":4,"entry_index":0,"source_chapter":4,"verse":11}}],"12":[{"match":"direct","source_href":"../../ellicott/colossians/4.htm","source_id":"ellicott","source_name":"Ellicott's Commentary for English Readers","source_ref":{"book_id":"colossians","chapter":4,"entry_index":0,"source_chapter":4,"verse":12}},{"match":"direct","source_href":"../../pulpit/colossians/4.htm","source_id":"pulpit","source_name":"Pulpit Commentary","source_ref":{"book_id":"colossians","chapter":4,"entry_index":0,"source_chapter":4,"verse":12}},{"match":"hash","source_href":"../../mhc/colossians/4.htm","source_id":"mhc","source_name":"Matthew Henry's Concise Commentary","source_ref":{"book_id":"colossians","chapter":4,"entry_index":0,"source_chapter":4,"verse":10},"text_hash":"043e21e3c6a088c85d12faa6cdc25ef67d3515fc"},{"match":"direct","source_href":"../../gill/colossians/4.htm","source_id":"gill","source_name":"Gill's Exposition of the Entire Bible","source_ref":{"book_id":"colossians","chapter":4,"entry_index":0,"source_chapter":4,"verse":12}}],"13":[{"match":"direct","source_href":"../../ellicott/colossians/4.htm","source_id":"ellicott","source_name":"Ellicott's Commentary for English Readers","source_ref":{"book_id":"colossians","chapter":4,"entry_index":0,"source_chapter":4,"verse":13}},{"match":"direct","source_href":"../../pulpit/colossians/4.htm","source_id":"pulpit","source_name":"Pulpit Commentary","source_ref":{"book_id":"colossians","chapter":4,"entry_index":0,"source_chapter":4,"verse":13}},{"match":"hash","source_href":"../../mhc/colossians/4.htm","source_id":"mhc","source_name":"Matthew Henry's Concise Commentary","source_ref":{"book_id":"colossians","chapter":4,"entry_index":0,"source_chapter":4,"verse":10},"text_hash":"043e21e3c6a088c85d12faa6cdc25ef67d3515fc"},{"match":"direct","source_href":"../../gill/colossians/4.htm","source_id":"gill","source_name":"Gill's Exposition of the Entire Bible","source_ref":{"book_id":"colossians","chapter":4,"entry_index":0,"source_chapter":4,"verse":13}}],"14":[{"match":"direct","source_href":"../../ellicott/colossians/4.htm","source_id":"ellicott","source_name":"Ellicott's Commentary for English Readers","source_ref":{"book_id":"colossians","chapter":4,"entry_index":0,"source_chapter":4,"verse":14}},{"match":"direct","source_href":"../../pulpit/colossians/4.htm","source_id":"pulpit","source_name":"Pulpit Commentary","source_ref":{"book_id":"colossians","chapter":4,"entry_index":0,"source_chapter":4,"verse":14}},{"match":"hash","source_href":"../../mhc/colossians/4.htm","source_id":"mhc","source_name":"Matthew Henry's Concise Commentary","source_ref":{"book_id":"colossians","chapter":4,"entry_index":0,"source_chapter":4,"verse":10},"text_hash":"043e21e3c6a088c85d12faa6cdc25ef67d3515fc"},{"match":"direct","source_href":"../../gill/colossians/4.htm","source_id":"gill","source_name":"Gill's Exposition of the Entire Bible","source_ref":{"book_id":"colossians","chapter":4,"entry_index":0,"source_chapter":4,"verse":14}}],"15":[{"match":"direct","source_href":"../../ellicott/colossians/4.htm","source_id":"ellicott","source_name":"Ellicott's Commentary for English Readers","source_ref":{"book_id":"colossians","chapter":4,"entry_index":0,"source_chapter":4,"verse":15}},{"match":"direct","source_href":"../../pulpit/colossians/4.htm","source_id":"pulpit","source_name":"Pulpit Commentary","source_ref":{"book_id":"colossians","chapter":4,"entry_index":0,"source_chapter":4,"verse":15}},{"match":"hash","source_href":"../../mhc/colossians/4.htm","source_id":"mhc","source_name":"Matthew Henry's Concise Commentary","source_ref":{"book_id":"colossians","chapter":4,"entry_index":0,"source_chapter":4,"verse":10},"text_hash":"043e21e3c6a088c85d12faa6cdc25ef67d3515fc"},{"match":"direct","source_href":"../../gill/colossians/4.htm","source_id":"gill","source_name":"Gill's Exposition of the Entire Bible","source_ref":{"book_id":"colossians","chapter":4,"entry_index":0,"source_chapter":4,"verse":15}}],"16":[{"match":"direct","source_href":"../../ellicott/colossians/4.htm","source_id":"ellicott","source_name":"Ellicott's Commentary for English Readers","source_ref":{"book_id":"colossians","chapter":4,"entry_index":0,"source_chapter":4,"verse":16}},{"match":"direct","source_href":"../../pulpit/colossians/4.htm","source_id":"pulpit","source_name":"Pulpit Commentary","source_ref":{"book_id":"colossians","chapter":4,"entry_index":0,"source_chapter":4,"verse":16}},{"match":"hash","source_href":"../../mhc/colossians/4.htm","source_id":"mhc","source_name":"Matthew Henry's Concise Commentary","source_ref":{"book_id":"colossians","chapter":4,"entry_index":0,"source_chapter":4,"verse":10},"text_hash":"043e21e3c6a088c85d12faa6cdc25ef67d3515fc"},{"match":"direct","source_href":"../../gill/colossians/4.htm","source_id":"gill","source_name":"Gill's Exposition of the Entire Bible","source_ref":{"book_id":"colossians","chapter":4,"entry_index":0,"source_chapter":4,"verse":16}}],"17":[{"match":"direct","source_href":"../../ellicott/colossians/4.htm","source_id":"ellicott","source_name":"Ellicott's Commentary for English Readers","source_ref":{"book_id":"colossians","chapter":4,"entry_index":0,"source_chapter":4,"verse":17}},{"match":"direct","source_href":"../../pulpit/colossians/4.htm","source_id":"pulpit","source_name":"Pulpit Commentary","source_ref":{"book_id":"colossians","chapter":4,"entry_index":0,"source_chapter":4,"verse":17}},{"match":"hash","source_href":"../../mhc/colossians/4.htm","source_id":"mhc","source_name":"Matthew Henry's Concise Commentary","source_ref":{"book_id":"colossians","chapter":4,"entry_index":0,"source_chapter":4,"verse":10},"text_hash":"043e21e3c6a088c85d12faa6cdc25ef67d3515fc"},{"match":"direct","source_href":"../../gill/colossians/4.htm","source_id":"gill","source_name":"Gill's Exposition of the Entire Bible","source_ref":{"book_id":"colossians","chapter":4,"entry_index":0,"source_chapter":4,"verse":17}}],"18":[{"match":"direct","source_href":"../../ellicott/colossians/4.htm","source_id":"ellicott","source_name":"Ellicott's Commentary for English Readers","source_ref":{"book_id":"colossians","chapter":4,"entry_index":0,"source_chapter":4,"verse":18}},{"match":"direct","source_href":"../../pulpit/colossians/4.htm","source_id":"pulpit","source_name":"Pulpit Commentary","source_ref":{"book_id":"colossians","chapter":4,"entry_index":0,"source_chapter":4,"verse":18}},{"match":"hash","source_href":"../../mhc/colossians/4.htm","source_id":"mhc","source_name":"Matthew Henry's Concise Commentary","source_ref":{"book_id":"colossians","chapter":4,"entry_index":0,"source_chapter":4,"verse":10},"text_hash":"043e21e3c6a088c85d12faa6cdc25ef67d3515fc"},{"commentary_html":"The salutation by the hand of me Paul,.... After his amanuensis had finished the epistle, he added his usual salutation to it with his own hand, to prevent all counterfeits and impositions, and that the churches to whom he wrote might be sure of the genuineness of his epistles; but before he added it to it, he either wrote with his own hand, or ordered to be written the following words, <p>remember my bonds; this he says, partly that they might be animated to abide by the Gospel, for which, as he had told them before, <a href=\"../../par/colossians/4-3.htm\">Colossians 4:3</a> that he was in bonds; and partly to encourage them, by his example, patiently to endure what afflictions and persecutions soever they should meet with, for the sake of it; as also that they might be moved hereby, to remember him in their prayers, that, if it was the will of God, he might be released, and be yet further useful in preaching the Gospel; or however, that he might be supported in his bonds, and cheerfully bear them, and remain steadfast in his faith in Christ unto the end: and then follows the salutation, <p>grace be with you, Amen; which is common to all his epistles, and well suits them; in which he so much displays the grace of God, as it is expressed in the Gospel; and which his heart was full of, and earnestly desired might be more largely manifested to, and bestowed upon the saints. This epistle is said to be <p>written from Rome to the Colossians, by Tychicus and Onesimus; and though the subscriptions of the epistles are not always to be depended on, yet this seems to be right; that it was inscribed to the Colossians, there is no doubt; and that it was written from Rome is clear enough, since by several expressions it is plain that he was now a prisoner, and in bonds; and that it was sent by Tychicus and Onesimus is more than probable, from <a href=\"../../par/colossians/4-7.htm\">Colossians 4:7</a>.","content_hash":"905a2b2afa143aa70a128f4c39598be7c772bea0","links":[{"book_id":"colossians","chapter":4,"href":"../../par/colossians/4-3.htm","label":"Colossians 4:3","verse_end":3,"verse_start":3},{"book_id":"colossians","chapter":4,"href":"../../par/colossians/4-7.htm","label":"Colossians 4:7","verse_end":7,"verse_start":7}],"source_href":"../../gill/colossians/4.htm","source_id":"gill","source_name":"Gill's Exposition of the Entire Bible","text_hash":"aa63f32073f12f7304bc56e99383dbfc6e9ed63d"}],"2":[{"match":"direct","source_href":"../../ellicott/colossians/4.htm","source_id":"ellicott","source_name":"Ellicott's Commentary for English Readers","source_ref":{"book_id":"colossians","chapter":4,"entry_index":0,"source_chapter":4,"verse":2}},{"match":"direct","source_href":"../../pulpit/colossians/4.htm","source_id":"pulpit","source_name":"Pulpit Commentary","source_ref":{"book_id":"colossians","chapter":4,"entry_index":0,"source_chapter":4,"verse":2}},{"match":"direct","source_href":"../../mhc/colossians/4.htm","source_id":"mhc","source_name":"Matthew Henry's Concise Commentary","source_ref":{"book_id":"colossians","chapter":4,"entry_index":0,"source_chapter":4,"verse":2}},{"match":"direct","source_href":"../../gill/colossians/4.htm","source_id":"gill","source_name":"Gill's Exposition of the Entire Bible","source_ref":{"book_id":"colossians","chapter":4,"entry_index":0,"source_chapter":4,"verse":2}}],"3":[{"match":"direct","source_href":"../../ellicott/colossians/4.htm","source_id":"ellicott","source_name":"Ellicott's Commentary for English Readers","source_ref":{"book_id":"colossians","chapter":4,"entry_index":0,"source_chapter":4,"verse":3}},{"match":"direct","source_href":"../../pulpit/colossians/4.htm","source_id":"pulpit","source_name":"Pulpit Commentary","source_ref":{"book_id":"colossians","chapter":4,"entry_index":0,"source_chapter":4,"verse":3}},{"match":"hash","source_href":"../../mhc/colossians/4.htm","source_id":"mhc","source_name":"Matthew Henry's Concise Commentary","source_ref":{"book_id":"colossians","chapter":4,"entry_index":0,"source_chapter":4,"verse":2},"text_hash":"64c75afc508e87912dc6c03622a9c7bc343898d7"},{"match":"direct","source_href":"../../gill/colossians/4.htm","source_id":"gill","source_name":"Gill's Exposition of the Entire Bible","source_ref":{"book_id":"colossians","chapter":4,"entry_index":0,"source_chapter":4,"verse":3}}],"4":[{"match":"direct","source_href":"../../pulpit/colossians/4.htm","source_id":"pulpit","source_name":"Pulpit Commentary","source_ref":{"book_id":"colossians","chapter":4,"entry_index":0,"source_chapter":4,"verse":4}},{"match":"hash","source_href":"../../mhc/colossians/4.htm","source_id":"mhc","source_name":"Matthew Henry's Concise Commentary","source_ref":{"book_id":"colossians","chapter":4,"entry_index":0,"source_chapter":4,"verse":2},"text_hash":"64c75afc508e87912dc6c03622a9c7bc343898d7"},{"match":"direct","source_href":"../../gill/colossians/4.htm","source_id":"gill","source_name":"Gill's Exposition of the Entire Bible","source_ref":{"book_id":"colossians","chapter":4,"entry_index":0,"source_chapter":4,"verse":4}}],"5":[{"match":"direct","source_href":"../../ellicott/colossians/4.htm","source_id":"ellicott","source_name":"Ellicott's Commentary for English Readers","source_ref":{"book_id":"colossians","chapter":4,"entry_index":0,"source_chapter":4,"verse":5}},{"match":"direct","source_href":"../../pulpit/colossians/4.htm","source_id":"pulpit","source_name":"Pulpit Commentary","source_ref":{"book_id":"colossians","chapter":4,"entry_index":0,"source_chapter":4,"verse":5}},{"match":"hash","source_href":"../../mhc/colossians/4.htm","source_id":"mhc","source_name":"Matthew Henry's Concise Commentary","source_ref":{"book_id":"colossians","chapter":4,"entry_index":0,"source_chapter":4,"verse":2},"text_hash":"64c75afc508e87912dc6c03622a9c7bc343898d7"},{"match":"direct","source_href":"../../gill/colossians/4.htm","source_id":"gill","source_name":"Gill's Exposition of the Entire Bible","source_ref":{"book_id":"colossians","chapter":4,"entry_index":0,"source_chapter":4,"verse":5}}],"6":[{"match":"direct","source_href":"../../ellicott/colossians/4.htm","source_id":"ellicott","source_name":"Ellicott's Commentary for English Readers","source_ref":{"book_id":"colossians","chapter":4,"entry_index":0,"source_chapter":4,"verse":6}},{"match":"direct","source_href":"../../pulpit/colossians/4.htm","source_id":"pulpit","source_name":"Pulpit Commentary","source_ref":{"book_id":"colossians","chapter":4,"entry_index":0,"source_chapter":4,"verse":6}},{"match":"hash","source_href":"../../mhc/colossians/4.htm","source_id":"mhc","source_name":"Matthew Henry's Concise Commentary","source_ref":{"book_id":"colossians","chapter":4,"entry_index":0,"source_chapter":4,"verse":2},"text_hash":"64c75afc508e87912dc6c03622a9c7bc343898d7"},{"match":"direct","source_href":"../../gill/colossians/4.htm","source_id":"gill","source_name":"Gill's Exposition of the Entire Bible","source_ref":{"book_id":"colossians","chapter":4,"entry_index":0,"source_chapter":4,"verse":6}}],"7":[{"match":"direct","source_href":"../../ellicott/colossians/4.htm","source_id":"ellicott","source_name":"Ellicott's Commentary for English Readers","source_ref":{"book_id":"colossians","chapter":4,"entry_index":0,"source_chapter":4,"verse":7}},{"match":"direct","source_href":"../../pulpit/colossians/4.htm","source_id":"pulpit","source_name":"Pulpit Commentary","source_ref":{"book_id":"colossians","chapter":4,"entry_index":0,"source_chapter":4,"verse":7}},{"match":"direct","source_href":"../../mhc/colossians/4.htm","source_id":"mhc","source_name":"Matthew Henry's Concise Commentary","source_ref":{"book_id":"colossians","chapter":4,"entry_index":0,"source_chapter":4,"verse":7}},{"match":"direct","source_href":"../../gill/colossians/4.htm","source_id":"gill","source_name":"Gill's Exposition of the Entire Bible","source_ref":{"book_id":"colossians","chapter":4,"entry_index":0,"source_chapter":4,"verse":7}}],"8":[{"match":"direct","source_href":"../../pulpit/colossians/4.htm","source_id":"pulpit","source_name":"Pulpit Commentary","source_ref":{"book_id":"colossians","chapter":4,"entry_index":0,"source_chapter":4,"verse":8}},{"match":"hash","source_href":"../../mhc/colossians/4.htm","source_id":"mhc","source_name":"Matthew Henry's Concise Commentary","source_ref":{"book_id":"colossians","chapter":4,"entry_index":0,"source_chapter":4,"verse":7},"text_hash":"609340e8371290383998d087ef930c542750e1bd"},{"match":"direct","source_href":"../../gill/colossians/4.htm","source_id":"gill","source_name":"Gill's Exposition of the Entire Bible","source_ref":{"book_id":"colossians","chapter":4,"entry_index":0,"source_chapter":4,"verse":8}}],"9":[{"match":"direct","source_href":"../../ellicott/colossians/4.htm","source_id":"ellicott","source_name":"Ellicott's Commentary for English Readers","source_ref":{"book_id":"colossians","chapter":4,"entry_index":0,"source_chapter":4,"verse":9}},{"match":"direct","source_href":"../../pulpit/colossians/4.htm","source_id":"pulpit","source_name":"Pulpit Commentary","source_ref":{"book_id":"colossians","chapter":4,"entry_index":0,"source_chapter":4,"verse":9}},{"match":"hash","source_href":"../../mhc/colossians/4.htm","source_id":"mhc","source_name":"Matthew Henry's Concise Commentary","source_ref":{"book_id":"colossians","chapter":4,"entry_index":0,"source_chapter":4,"verse":7},"text_hash":"609340e8371290383998d087ef930c542750e1bd"},{"match":"direct","source_href":"../../gill/colossians/4.htm","source_id":"gill","source_name":"Gill's Exposition of the Entire Bible","source_ref":{"book_id":"colossians","chapter":4,"entry_index":0,"source_chapter":4,"verse":9}}]}}}