{"book":{"id":"obadiah","name":"Obadiah","osis":"Obad"},"chapters":{"1":{"1":[[1,"The vision","hebrew","H2377",2377,"chazown","","vision"],[2,"of Obadiah","hebrew","H5662",5662,"Obadyah","","'servant of Yah,' the name of a number of Isr."],[3,"Thus saith","hebrew","H559",559,"'amar","","to utter, say"],[4,"the Lord","hebrew","H136",136,"'Adonay","","Lord"],[5,"GOD","hebrew","H3069",3069,"Yhovih","","God"],[6,"concerning Edom","hebrew","H123",123,"'Edom","","the name of a condiment"],[7,"We have heard","hebrew","H8085",8085,"shama'","","to hear"],[8,"a rumour","hebrew","H8052",8052,"shmuw'ah","","a report"],[9,"from the LORD","hebrew","H3068",3068,"Yhovah","","the proper name of the God of Israel"],[10,"and an ambassador","hebrew","H6735",6735,"tsiyr","","ambassador"],[11,"is sent","hebrew","H7971",7971,"shalach","","to send"],[12,"among the heathen","hebrew","H1471",1471,"gowy","","nation, people"],[13,"Arise","hebrew","H6965",6965,"quwm","","to arise, stand up, stand"],[14,"ye, and let us rise up","hebrew","H6965",6965,"quwm","","to arise, stand up, stand"],[15,"against her in battle","hebrew","H4421",4421,"milchamah","","a battle, war"]],"2":[[1,"Behold, I have made","hebrew","H5414",5414,"nathan","","to give, put, set"],[2,"thee small","hebrew","H6996",6996,"qatan","","least"],[3,"among the heathen","hebrew","H1471",1471,"gowy","","nation, people"],[4,"thou art greatly","hebrew","H3966",3966,"m'od","","muchness, force, abundance"],[5,"despised","hebrew","H959",959,"bazah","","to despise"]],"3":[[1,"The pride","hebrew","H2087",2087,"zadown","","insolence, presumptuousness"],[2,"of thine heart","hebrew","H3820",3820,"leb","","inner man, mind, will, heart"],[3,"hath deceived","hebrew","H5377",5377,"nasha'","","to lend on interest, be a creditor"],[4,"thee, thou that dwellest","hebrew","H7931",7931,"shakan","","to settle down, abide, dwell"],[5,"in the clefts","hebrew","H2288",2288,"chagav","","places of concealment, retreats"],[6,"of the rock","hebrew","H5553",5553,"cela'","","a crag, cliff"],[7,"whose habitation","hebrew","H3427",3427,"yashab","","to sit, remain, dwell"],[8,"","hebrew","H4791",4791,"marowm","","height"],[9,"that saith","hebrew","H559",559,"'amar","","to utter, say"],[10,"in his heart","hebrew","H3820",3820,"leb","","inner man, mind, will, heart"],[11,"Who shall bring me down","hebrew","H3381",3381,"yarad","","to come or go down, descend"],[12,"to the ground","hebrew","H776",776,"'erets","","earth, land"]],"4":[[1,"Though thou exalt","hebrew","H1361",1361,"gabahh","","exalt"],[2,"","hebrew","H5404",5404,"nesher","","an eagle"],[3,"and though thou set","hebrew","H7760",7760,"suwm","","to put, place, set"],[4,"thy nest","hebrew","H7064",7064,"qen","","a nest"],[5,"among the stars","hebrew","H3556",3556,"kowkab","","a star"],[6,"thence will I bring thee down","hebrew","H3381",3381,"yarad","","to come or go down, descend"],[7,"saith","hebrew","H5002",5002,"n'um","","utterance"],[8,"the LORD","hebrew","H3068",3068,"Yhovah","","the proper name of the God of Israel"]],"5":[[1,"If thieves","hebrew","H1590",1590,"gannab","","a thief"],[2,"came","hebrew","H935",935,"bow'","","to come in, come, go in, go"],[3,"to thee, if robbers","hebrew","H7703",7703,"shadad","","to deal violently with, despoil, devastate, ruin"],[4,"by night","hebrew","H3915",3915,"layil","","night"],[5,"how art thou cut off","hebrew","H1820",1820,"damah","","to cease, cause to cease, cut off, destroy"],[6,"would they not have stolen","hebrew","H1589",1589,"ganab","","to steal"],[7,"till they had enough","hebrew","H1767",1767,"day","","sufficiency, enough"],[8,"if the grapegatherers","hebrew","H1219",1219,"batsar","","to cut off, make inaccessible, enclose"],[9,"came","hebrew","H935",935,"bow'","","to come in, come, go in, go"],[10,"to thee, would they not leave","hebrew","H7604",7604,"sha'ar","","to remain, be left over"],[11,"","hebrew","H5955",5955,"olelah","","a gleaning"]],"6":[[1,"How are","hebrew","H6215",6215,"Esav","","oldest son of Isaac"],[2,"searched out","hebrew","H2664",2664,"chaphas","","to search"],[3,"","hebrew","H4710",4710,"mitspun","","hidden treasure, treasure"],[4,"things sought up","hebrew","H1158",1158,"ba'ah","","to inquire, cause to swell or boil up"]],"7":[[1,"All the men","hebrew","H582",582,"'enowsh","","man, mankind"],[2,"of thy confederacy","hebrew","H1285",1285,"briyth","","a covenant"],[3,"have brought","hebrew","H7971",7971,"shalach","","to send"],[4,"thee","hebrew","H1366",1366,"gbuwl","","border, boundary, territory"],[5,"the men","hebrew","H582",582,"'enowsh","","man, mankind"],[6,"that were at peace","hebrew","H7965",7965,"shalowm","","completeness, soundness, welfare, peace"],[7,"with thee have deceived","hebrew","H5377",5377,"nasha'","","to lend on interest, be a creditor"],[8,"thee,","hebrew","H3201",3201,"yakol","","to be able, have power"],[9,"against thee;","hebrew","H3899",3899,"lechem","","bread, food"],[10,"have laid","hebrew","H7760",7760,"suwm","","to put, place, set"],[11,"a wound","hebrew","H4204",4204,"mazowr","","perhaps a net"],[12,"under thee:","hebrew","H8394",8394,"tabuwn","","an understanding"]],"8":[[1,"Shall I not in that day","hebrew","H3117",3117,"yowm","","day"],[2,"saith","hebrew","H5002",5002,"n'um","","utterance"],[3,"the LORD","hebrew","H3068",3068,"Yhovah","","the proper name of the God of Israel"],[4,"even destroy","hebrew","H6",6,"'abad","","to perish"],[5,"the wise","hebrew","H2450",2450,"chakam","","wise"],[6,"","hebrew","H123",123,"'Edom","","the name of a condiment"],[7,"and understanding","hebrew","H8394",8394,"tabuwn","","an understanding"],[8,"out of the mount","hebrew","H2022",2022,"har","","mountain, hill, hill country"],[9,"of Esau","hebrew","H6215",6215,"Esav","","oldest son of Isaac"]],"9":[[1,"And thy mighty","hebrew","H1368",1368,"gibbowr","","strong, mighty"],[2,"","hebrew","H8487",8487,"Teyman","","a N. district of Edom, also an Edomite chief"],[3,"shall be dismayed","hebrew","H2865",2865,"chathath","","to be shattered or dismayed"],[4,"to the end that every one","hebrew","H376",376,"'iysh","","man"],[5,"of the mount","hebrew","H2022",2022,"har","","mountain, hill, hill country"],[6,"of Esau","hebrew","H6215",6215,"Esav","","oldest son of Isaac"],[7,"may be cut off","hebrew","H3772",3772,"karath","","to cut off, cut down"],[8,"by slaughter","hebrew","H6993",6993,"qetel","","slaughter"]],"10":[[1,"For","hebrew","H2555",2555,"chamac","","violence, wrong"],[2,"against thy brother","hebrew","H251",251,"'ach","","a brother"],[3,"Jacob","hebrew","H3290",3290,"Ya'aqob","","a son of Isaac, also his desc."],[4,"shame","hebrew","H955",955,"buwshah","","shame"],[5,"shall cover","hebrew","H3680",3680,"kacah","","to cover"],[6,"thee, and thou shalt be cut off","hebrew","H3772",3772,"karath","","to cut off, cut down"],[7,"for ever","hebrew","H5769",5769,"owlam","","long duration, antiquity, futurity"]],"11":[[1,"In the day","hebrew","H3117",3117,"yowm","","day"],[2,"that thou stoodest","hebrew","H5975",5975,"amad","","to take one's stand, stand"],[3,"on the other side, in the day","hebrew","H3117",3117,"yowm","","day"],[4,"that the strangers","hebrew","H2114",2114,"zuwr","","another"],[5,"carried away captive","hebrew","H7617",7617,"shabah","","to take captive"],[6,"his forces","hebrew","H2428",2428,"chayil","","strength, efficiency, wealth, army"],[7,"and foreigners","hebrew","H5237",5237,"nokriy","","foreign, alien"],[8,"entered","hebrew","H935",935,"bow'","","to come in, come, go in, go"],[9,"into his gates","hebrew","H8179",8179,"sha'ar","","a gate"],[10,"and cast","hebrew","H3032",3032,"yadad","","to cast a lot"],[11,"lots","hebrew","H1486",1486,"gowral","","a lot (for casting)"],[12,"upon Jerusalem","hebrew","H3389",3389,"Yruwshalaim","","probably 'foundation of peace,' capital city of all Isr."],[13,"even thou","hebrew","H259",259,"'echad","","one"]],"12":[[1,"But thou shouldest not have looked","hebrew","H7200",7200,"ra'ah","","to see"],[2,"on the day","hebrew","H3117",3117,"yowm","","day"],[3,"of thy brother","hebrew","H251",251,"'ach","","a brother"],[4,"in the day","hebrew","H3117",3117,"yowm","","day"],[5,"that he became a stranger","hebrew","H5235",5235,"neker","","strange"],[6,"neither shouldest thou have rejoiced","hebrew","H8055",8055,"samach","","rejoice, be glad"],[7,"over the children","hebrew","H1121",1121,"ben","","son"],[8,"of Judah","hebrew","H3063",3063,"Yhuwdah","","probably 'praised,' a son of Jacob, also his desc., the S. kingdom, also four Israelites"],[9,"in the day","hebrew","H3117",3117,"yowm","","day"],[10,"of their destruction","hebrew","H6",6,"'abad","","to perish"],[11,"neither shouldest thou have spoken","hebrew","H6310",6310,"peh","","mouth"],[12,"proudly","hebrew","H1431",1431,"gadal","","to grow up, become great"],[13,"in the day","hebrew","H3117",3117,"yowm","","day"],[14,"of distress","hebrew","H6869",6869,"tsarah","","adversary"]],"13":[[1,"Thou shouldest not have entered","hebrew","H935",935,"bow'","","to come in, come, go in, go"],[2,"into the gate","hebrew","H8179",8179,"sha'ar","","a gate"],[3,"of my people","hebrew","H5971",5971,"am","","folk"],[4,"in the day","hebrew","H3117",3117,"yowm","","day"],[5,"of their calamity","hebrew","H343",343,"'eyd","","distress, calamity"],[6,"yea, thou shouldest not have looked","hebrew","H7200",7200,"ra'ah","","to see"],[7,"on their affliction","hebrew","H7451",7451,"ra'","","adversity"],[8,"in the day","hebrew","H3117",3117,"yowm","","day"],[9,"of their calamity","hebrew","H343",343,"'eyd","","distress, calamity"],[10,"nor have laid","hebrew","H7971",7971,"shalach","","to send"],[11,"","hebrew","H2428",2428,"chayil","","strength, efficiency, wealth, army"],[12,"in the day","hebrew","H3117",3117,"yowm","","day"],[13,"of their calamity","hebrew","H343",343,"'eyd","","distress, calamity"]],"14":[[1,"Neither shouldest thou have stood","hebrew","H5975",5975,"amad","","to take one's stand, stand"],[2,"in the crossway","hebrew","H6563",6563,"pereq","","parting of ways, plunder"],[3,"to cut off","hebrew","H3772",3772,"karath","","to cut off, cut down"],[4,"those of his that did escape","hebrew","H6412",6412,"paliyt","","escaped"],[5,"neither shouldest thou have delivered up","hebrew","H5462",5462,"cagar","","to shut, close"],[6,"those of his that did remain","hebrew","H8300",8300,"sariyd","","a survivor"],[7,"in the day","hebrew","H3117",3117,"yowm","","day"],[8,"of distress","hebrew","H6869",6869,"tsarah","","adversary"]],"15":[[1,"For the day","hebrew","H3117",3117,"yowm","","day"],[2,"of the LORD","hebrew","H3068",3068,"Yhovah","","the proper name of the God of Israel"],[3,"","hebrew","H7138",7138,"qarowb","","near"],[4,"upon all the heathen","hebrew","H1471",1471,"gowy","","nation, people"],[5,"as thou hast done","hebrew","H6213",6213,"asah","","accomplish"],[6,"it shall be done","hebrew","H6213",6213,"asah","","accomplish"],[7,"unto thee: thy reward","hebrew","H1576",1576,"gmuwl","","a dealing, recompense, benefit"],[8,"shall return","hebrew","H7725",7725,"shuwb","","to turn back, return"],[9,"upon thine own head","hebrew","H7218",7218,"ro'sh","","head"]],"16":[[1,"For as ye have drunk","hebrew","H8354",8354,"shathah","","to drink"],[2,"upon my holy","hebrew","H6944",6944,"qodesh","","apartness, sacredness"],[3,"mountain","hebrew","H2022",2022,"har","","mountain, hill, hill country"],[4,"","hebrew","H1471",1471,"gowy","","nation, people"],[5,"drink","hebrew","H8354",8354,"shathah","","to drink"],[6,"continually","hebrew","H8548",8548,"tamiyd","","continuity"],[7,"yea, they shall drink","hebrew","H8354",8354,"shathah","","to drink"],[8,"and they shall swallow down","hebrew","H3886",3886,"luwa'","","swallow"],[9,"and they shall be as though they had not","hebrew","H3808",3808,"lo'","","not"]],"17":[[1,"But upon mount","hebrew","H2022",2022,"har","","mountain, hill, hill country"],[2,"Zion","hebrew","H6726",6726,"Tsiyown","","a mountain in Jer., also a name for Jer."],[3,"shall be deliverance","hebrew","H6413",6413,"pleytah","","an escape"],[4,"and there shall be holiness","hebrew","H6944",6944,"qodesh","","apartness, sacredness"],[5,"and the house","hebrew","H1004",1004,"bayith","","a house"],[6,"of Jacob","hebrew","H3290",3290,"Ya'aqob","","a son of Isaac, also his desc."],[7,"shall possess","hebrew","H3423",3423,"yarash","","to take possession of, inherit, dispossess"],[8,"their possessions","hebrew","H4180",4180,"mowrash","","a possession"]],"18":[[1,"And the house","hebrew","H1004",1004,"bayith","","a house"],[2,"of Jacob","hebrew","H3290",3290,"Ya'aqob","","a son of Isaac, also his desc."],[3,"shall be a fire","hebrew","H784",784,"'esh","","a fire"],[4,"and the house","hebrew","H1004",1004,"bayith","","a house"],[5,"of Joseph","hebrew","H3130",3130,"Yowceph","","'he increases,' a son of Jacob, also the name of several Israelites"],[6,"a flame","hebrew","H3852",3852,"lehabah","","flame, blade"],[7,"and the house","hebrew","H1004",1004,"bayith","","a house"],[8,"of Esau","hebrew","H6215",6215,"Esav","","oldest son of Isaac"],[9,"for stubble","hebrew","H7179",7179,"qash","","stubble, chaff"],[10,"and they shall kindle","hebrew","H1814",1814,"dalaq","","to burn, hotly pursue"],[11,"in them, and devour","hebrew","H398",398,"'akal","","to eat"],[12,"them; and there shall not be","hebrew","H8300",8300,"sariyd","","a survivor"],[13,"of the house","hebrew","H1004",1004,"bayith","","a house"],[14,"of Esau","hebrew","H6215",6215,"Esav","","oldest son of Isaac"],[15,"for the LORD","hebrew","H3068",3068,"Yhovah","","the proper name of the God of Israel"],[16,"hath spoken","hebrew","H1696",1696,"dabar","","to speak"]],"19":[[1,"And","hebrew","H5045",5045,"negeb","","south country, the Negeb, south"],[2,"shall possess","hebrew","H3423",3423,"yarash","","to take possession of, inherit, dispossess"],[3,"the mount","hebrew","H2022",2022,"har","","mountain, hill, hill country"],[4,"of Esau","hebrew","H6215",6215,"Esav","","oldest son of Isaac"],[5,"and","hebrew","H8219",8219,"shphelah","","lowland"],[6,"the Philistines","hebrew","H6430",6430,"Plishtiy","","inhab. of Philistia"],[7,"and they shall possess","hebrew","H3423",3423,"yarash","","to take possession of, inherit, dispossess"],[8,"the fields","hebrew","H7704",7704,"sadeh","","field, land"],[9,"of Ephraim","hebrew","H669",669,"'Ephrayim","","a son of Joseph, also his desc. and their territory"],[10,"and the fields","hebrew","H7704",7704,"sadeh","","field, land"],[11,"of Samaria","hebrew","H8111",8111,"Shomrown","","capital of N. kingdom of Isr."],[12,"and Benjamin","hebrew","H1144",1144,"Binyamiyn","","'son of (the) right hand,' youngest son of Jacob, also the name of two other Isr ."],[13,"shall","hebrew","H1568",1568,"Gil'ad","","a region in Palestine, also the name of several Israelites"]],"20":[[1,"And the captivity","hebrew","H1546",1546,"galuwth","","an exile"],[2,"of this host","hebrew","H2426",2426,"cheyl","","rampart, fortress"],[3,"of the children","hebrew","H1121",1121,"ben","","son"],[4,"of Israel","hebrew","H3478",3478,"Yisra'el","","'God strives,' another name of Jacob and his desc."],[5,"shall","hebrew","H3669",3669,"Kna'aniy","","Canaanite"],[6,"","hebrew","H6886",6886,"Tsarphath","","'smelting place,' a city South of Sidon"],[7,"and the captivity","hebrew","H1546",1546,"galuwth","","an exile"],[8,"of Jerusalem","hebrew","H3389",3389,"Yruwshalaim","","probably 'foundation of peace,' capital city of all Isr."],[9,"which","hebrew","H5614",5614,"Cpharad","","the location of some exiles"],[10,"shall possess","hebrew","H3423",3423,"yarash","","to take possession of, inherit, dispossess"],[11,"the cities","hebrew","H5892",5892,"iyr","","excitement"],[12,"of the south","hebrew","H5045",5045,"negeb","","south country, the Negeb, south"]],"21":[[1,"And saviours","hebrew","H3467",3467,"yasha'","","to deliver"],[2,"shall come up","hebrew","H5927",5927,"alah","","to go up, ascend, climb"],[3,"on mount","hebrew","H2022",2022,"har","","mountain, hill, hill country"],[4,"Zion","hebrew","H6726",6726,"Tsiyown","","a mountain in Jer., also a name for Jer."],[5,"to judge","hebrew","H8199",8199,"shaphat","","to judge, govern"],[6,"the mount","hebrew","H2022",2022,"har","","mountain, hill, hill country"],[7,"of Esau","hebrew","H6215",6215,"Esav","","oldest son of Isaac"],[8,"and the kingdom","hebrew","H4410",4410,"mluwkah","","kingship, royalty"],[9,"shall be the LORD'S","hebrew","H3068",3068,"Yhovah","","the proper name of the God of Israel"]]}}}